Workbook
Name SegmentaçãodeDados_Taxa: #N/A

Sheet DIN_For
A3: Sum of Pago | B3: Rótulos de Coluna
B4: 2025 | C4: 2026 | H4: 2026 Total | I4: (vazio) | J4: (vazio) Total | K4: Total Geral
C5: jan | D5: fev | E5: mar | F5: abr | G5: mai | I5: <02/01/2025
A6: Rótulos de Linha
A7: ITAU UNIBANCO S.A. | B7: 392933.77 | C7: 29305.32 | D7: 28000.93 | E7: 28015.73 | F7: 25593.32 | G7: 23816.56 | H7: 134731.86 | K7: 527665.63
A8: FORTE DA GRANJA EMPREENDIMENTO IMOBILIARIO LTDA | B8: 347873.16 | C8: 27343.18 | D8: 27343.18 | E8: 25123.8 | F8: 28087.8 | G8: 28087.8 | H8: 135985.76 | K8: 483858.92
A9: MINISTERIO DA FAZENDA | B9: 248831.74 | C9: 20778.97 | D9: 18546.78 | E9: 19708.53 | F9: 18081.14 | G9: 18702.19 | H9: 95817.61 | K9: 344649.35
A10: GRAU T FRANQUIAS DE CURSOS TECNICOS LTDA. | B10: 203292.18 | C10: 10094.52 | D10: 20366.73 | E10: 17478.58 | F10: 24738.89 | G10: 23110.49 | H10: 95789.21 | K10: 299081.39
A11: EDITORA GRAU LTDA. | B11: 105519.3 | C11: 10698.66 | E11: 10702.08 | F11: 15153.55 | G11: 5350 | H11: 41904.29 | K11: 147423.59
A12: Associação Brasileira dos Franc | B12: 129034.06 | K12: 129034.06
A13: Lucia De Souza Leão Gouveia | B13: 56958.33 | C13: 12000 | D13: 12104 | E13: 12900 | F13: 12000 | G13: 12018.35 | H13: 61022.35 | K13: 117980.68
A14: FERNANDO AFONSO DOS SANTOS | B14: 64175.78 | C14: 7826.86 | D14: 9960 | E14: 9192 | F14: 9280.29 | G14: 8346 | H14: 44605.15 | K14: 108780.93
A15: Carlene Dos Santos | B15: 74988.28 | C15: 4278.62 | D15: 8150.42 | E15: 6411 | F15: 6526 | G15: 3545.62 | H15: 28911.66 | K15: 103899.94
A16: TIAGO PESSOA COSTA REIS | B16: 38460 | C16: 7266 | D16: 10346.72 | E16: 10346.72 | F16: 10346.72 | G16: 10346.72 | H16: 48652.88 | K16: 87112.88
A17: NIVEL A FRANQUIAS DE CURSOS DE FORMACAO PROFISSIONAL LTDA | B17: 48941.16 | C17: 7809.73 | D17: 8325.78 | E17: 7183.96 | F17: 8386.69 | G17: 6319.52 | H17: 38025.68 | K17: 86966.84
A18: FLASH BENEFICIOS - VT E VA | B18: 58623.34 | C18: 9468.6 | D18: 4384.28 | F18: 7583.57 | H18: 21436.45 | K18: 80059.79
A19: FACEBOOK SERVICOS ONLINE DO BR | B19: 46556.02 | C19: 6480.36 | D19: 7496.21 | E19: 7937 | F19: 4857.42 | G19: 4600 | H19: 31370.99 | K19: 77927.01
A20: FLASH TECNOLOGIA E INSTITUICAO DE PAGAMENTO LTDA | B20: 65379.81 | K20: 65379.81
A21: Thayna Cristine | B21: 40709.89 | C21: 4026.22 | D21: 5244.22 | E21: 7183.59 | F21: 3939.58 | G21: 3678.94 | H21: 24072.55 | K21: 64782.44
A22: FGTS - Fundo de garantia do tempo de serviço | B22: 34858.4 | C22: 6136.33 | D22: 4717.62 | E22: 4586.75 | F22: 5505.75 | G22: 1638.17 | H22: 22584.62 | K22: 57443.02
A23: Atacama Digital | B23: 51744.79 | K23: 51744.79
A24: Weslley Mateus Da Silva | B24: 30885.74 | C24: 2843 | D24: 4459.42 | E24: 4699.42 | F24: 4031 | G24: 4166.58 | H24: 20199.42 | K24: 51085.16
A25: Elisangela Da Silva Munarão | B25: 46068.87 | D25: 285.42 | H25: 285.42 | K25: 46354.29
A26: MACIEL BATISTA DE OLIVEIRA | B26: 27760 | C26: 2280 | D26: 3136 | E26: 2904 | F26: 5311 | G26: 3894 | H26: 17525 | K26: 45285
A27: EDSON JOSE DE MELO | B27: 26550.85 | C27: 2371 | D27: 4403.42 | E27: 4317.97 | F27: 4164.9 | G27: 3469.26 | H27: 18726.55 | K27: 45277.4
A28: Maria Sandra Santos Tavares | B28: 31360 | C28: 2260 | D28: 2940 | E28: 1932 | F28: 3128 | G28: 3592 | H28: 13852 | K28: 45212
A29: Google internet ltda | B29: 34245.02 | C29: 3514.58 | D29: 2498.73 | E29: 2058 | F29: 1197.9 | G29: 900 | H29: 10169.21 | K29: 44414.23
A30: Ana Beatriz Faustino Lopes | B30: 31742.46 | C30: 2980 | D30: 2720 | F30: 980 | G30: 3668 | H30: 10348 | K30: 42090.46
A31: Adriana da Silva Furlan | B31: 27564.52 | C31: 2539.1 | D31: 2638.02 | E31: 2916.02 | F31: 2622 | G31: 3123.42 | H31: 13838.56 | K31: 41403.08
A32: Marcilene de Jesus Duarte | B32: 27818.18 | C32: 4526.11 | D32: 1752.82 | E32: 1811.42 | F32: 2570.42 | G32: 2621.42 | H32: 13282.19 | K32: 41100.37
A33: ANE CAROLINA ARAUJO | B33: 30532.96 | C33: 1259 | D33: 1834.86 | E33: 970 | F33: 3353 | G33: 2202.62 | H33: 9619.48 | K33: 40152.44
A34: Elo camisetas Ltda | B34: 26337.78 | E34: 3179.78 | F34: 3192.21 | G34: 4944.5 | H34: 11316.49 | K34: 37654.27
A35: Kaio Felix de Macedo | B35: 22585.44 | C35: 2731 | D35: 2077.42 | E35: 3349.67 | F35: 2424 | G35: 4295.62 | H35: 14877.71 | K35: 37463.15
A36: Enel | B36: 14210.22 | C36: 4397.03 | D36: 4584.44 | E36: 4693.61 | F36: 4100.17 | G36: 5096.29 | H36: 22871.54 | K36: 37081.76
A37: Associação Brasileira dos Franc /NIVEL A | C37: 983.63 | D37: 8490.92 | E37: 7896.85 | F37: 9304.76 | G37: 10307.18 | H37: 36983.34 | K37: 36983.34
A38: QUALINFO SERVICOS DE INFORMATICA LTDA | B38: 23394.29 | C38: 1846.4 | D38: 1883.42 | E38: 1846.4 | F38: 1846.4 | G38: 1883.42 | H38: 9306.04 | K38: 32700.33
A39: João Victor Santos Costa | B39: 16669.69 | C39: 2772 | D39: 2898.38 | E39: 3396.14 | F39: 3001 | G39: 3523.1 | H39: 15590.62 | K39: 32260.31
A40: Cristina Pereira de Sena | B40: 21439.72 | C40: 1347 | D40: 1558.42 | E40: 1781.62 | F40: 2784.71 | G40: 499.02 | H40: 7970.77 | K40: 29410.49
A41: LETICIA NUNES DA FONSECA | B41: 20168.94 | C41: 1834.9 | D41: 495.42 | E41: 2076.83 | F41: 1816 | G41: 2577.86 | H41: 8801.01 | K41: 28969.95
A42: ELIANE FREIRES NEMET MARTINS | B42: 15220 | C42: 2160 | E42: 640 | F42: 5968 | G42: 4944 | H42: 13712 | K42: 28932
A43: Ricardo Da Silva Lino | B43: 16409.74 | C43: 2032 | D43: 2830.42 | E43: 2387.14 | F43: 1974 | G43: 2923.14 | H43: 12146.7 | K43: 28556.44
A44: WALDEMAR CAVALCANTI SOCIEDADE INDIVIDUAL DE ADVOCACIA | B44: 19308.58 | C44: 1621 | D44: 2121 | E44: 2154.49 | F44: 1621 | G44: 1621 | H44: 9138.49 | K44: 28447.07
A45: VINICIUS MARTINS DIAS BATISTA | B45: 28193.01 | K45: 28193.01
A46: CONSENSUS CONSULTORIA CONTABIL LTDA | B46: 18198.79 | C46: 3060.22 | D46: 1621 | E46: 1628.5 | F46: 1621 | G46: 1621 | H46: 9551.72 | K46: 27750.51
A47: Emerson Vieira | B47: 16241.96 | C47: 1925.25 | D47: 1993.42 | E47: 2769.12 | F47: 1872 | G47: 2703.12 | H47: 11262.91 | K47: 27504.87
A48: Naiara Oliveira Rodrigues | B48: 19821.39 | C48: 2359 | D48: 2081.42 | E48: 1222 | F48: 1600.17 | H48: 7262.59 | K48: 27083.98
A49: FABRICIO MARCELO SANTOS RODRIG | B49: 16915 | C49: 5320 | D49: 1550 | E49: 855 | F49: 800 | G49: 1020 | H49: 9545 | K49: 26460
A50: José Nilton Santos | B50: 18531.29 | C50: 1701 | D50: 1962.42 | E50: 3798.18 | H50: 7461.6 | K50: 25992.89
A51: Maria Lucia F. da Cunha | B51: 13132.54 | C51: 1991 | D51: 2158.82 | E51: 2344.02 | F51: 1869.4 | G51: 4014.5 | H51: 12377.74 | K51: 25510.28
A52: BRINGME SERVICOS DIGITAIS LTDA | B52: 15249.66 | C52: 1915.32 | D52: 2046.7 | E52: 2005.93 | F52: 2005.93 | G52: 2046.7 | H52: 10020.58 | K52: 25270.24
A53: JULIANA MARIA VICENTE BOTELHO | B53: 6263.98 | C53: 2859 | D53: 4354.42 | E53: 5047.18 | F53: 3979.9 | G53: 2462.38 | H53: 18702.88 | K53: 24966.86
A54: THAYNA COSTA PEREIRA | B54: 15382 | C54: 1440 | D54: 1848 | E54: 1848 | F54: 2604 | G54: 504 | H54: 8244 | K54: 23626
A55: VANDERLEIA DOS SANTOS OLIVEIRA | B55: 16320 | D55: 1680 | E55: 1600 | F55: 1440 | G55: 2560 | H55: 7280 | K55: 23600
A56: Atila Gandhi | B56: 21068.2 | C56: 1115.39 | H56: 1115.39 | K56: 22183.59
A57: Eliane Araujo Freires | B57: 13400 | D57: 3360 | E57: 3456 | H57: 6816 | K57: 20216
A58: STHEFANY DA SILVA FERREIRA | B58: 6396.72 | C58: 2687 | D58: 2334.42 | E58: 2372.66 | F58: 3103 | G58: 2869.9 | H58: 13366.98 | K58: 19763.7
A59: DARF | B59: 5410.93 | C59: 2661.14 | D59: 2614.42 | E59: 2691.94 | F59: 2865.32 | G59: 3183.41 | H59: 14016.23 | K59: 19427.16
A60: Alexandre da Silva Azevedo | B60: 5627.65 | C60: 1720 | D60: 3192 | E60: 2310 | F60: 2688 | G60: 2940 | H60: 12850 | K60: 18477.65
A61: Sabesp | B61: 8239.9 | C61: 2250.53 | D61: 1027.31 | E61: 2455.92 | F61: 1757.08 | G61: 2516.22 | H61: 10007.06 | K61: 18246.96
A62: Victor Tavares Vian | B62: 8967.4 | C62: 1299 | D62: 1769.6 | E62: 1323.4 | F62: 2367.82 | G62: 2456.4 | H62: 9216.22 | K62: 18183.62
A63: Henrique Lima Martins Lares | B63: 12577.72 | C63: 1872.6 | D63: 1720.42 | E63: 1864.22 | H63: 5457.24 | K63: 18034.96
A64: VANDA MARIA NASCIMENTO DA CUNHA | B64: 9640 | C64: 2040 | D64: 1120 | E64: 1980 | F64: 720 | G64: 2100 | H64: 7960 | K64: 17600
A65: MARIA DE FATIMA GUERRA | B65: 12160 | C65: 480 | F65: 3040 | G65: 1360 | H65: 4880 | K65: 17040
A66: MOLA TECNOLOGIA S.A. | B66: 16716.91 | K66: 16716.91
A67: OLIVIA PEREIRA GONCALVES | B67: 9000 | C67: 1500 | D67: 1500 | E67: 1500 | F67: 1500 | G67: 1500 | H67: 7500 | K67: 16500
A68: Artur Valente | B68: 16416 | K68: 16416
A69: Eduarda Oliveira Munarão | B69: 11737.16 | C69: 1797 | D69: 2809.68 | H69: 4606.68 | K69: 16343.84
A70: Samantha da Silva | B70: 14880 | D70: 644 | E70: 644 | H70: 1288 | K70: 16168
A71: Maria de Fatima Nunes | B71: 10960 | C71: 640 | D71: 520 | E71: 1040 | F71: 1620 | G71: 1360 | H71: 5180 | K71: 16140
A72: CLEITON PEREIRA DE OLIVEIRA | B72: 15844.4 | K72: 15844.4
A73: Luciene Lopes | B73: 15580 | K73: 15580
A74: JANAINA CRISTINA ALVES BORGES | B74: 13200 | E74: 1080 | F74: 720 | H74: 1800 | K74: 15000
A75: RC DIAGNOSTICO POR IMAGEM | B75: 9800 | C75: 910 | D75: 770 | E75: 1120 | F75: 1120 | G75: 1050 | H75: 4970 | K75: 14770
A76: CAIXA ECONOMICA FEDERAL | B76: 14728.53 | K76: 14728.53
A77: lais de castro | B77: 13320 | C77: 1120 | H77: 1120 | K77: 14440
A78: Guilherme Boyer Lino Souza | B78: 14308.79 | K78: 14308.79
A79: ALLDIX INFORMATICA LTDA | B79: 9551 | C79: 900 | D79: 900 | E79: 900 | F79: 900 | G79: 900 | H79: 4500 | K79: 14051
A80: 62.254.936 SAMIR FARAH | B80: 333 | C80: 2333 | D80: 3331 | E80: 3000 | F80: 2000 | G80: 3000 | H80: 13664 | K80: 13997
A81: Kauan Fernandes | B81: 10495.66 | C81: 1238.8 | D81: 750 | E81: 1500 | H81: 3488.8 | K81: 13984.46
A82: VALDEMIR BRANZAN RODRIGUES | B82: 10460 | C82: 400 | F82: 720 | G82: 2000 | H82: 3120 | K82: 13580
A83: CORPUS COMERCIAL E SERVICOS LTDA | B83: 7753 | D83: 1567 | E83: 824 | F83: 1454 | G83: 1440 | H83: 5285 | K83: 13038
A84: Beatriz Munarão | B84: 12981.04 | K84: 12981.04
A85: Dayane Pires de Souza | B85: 10546.81 | F85: 2000 | H85: 2000 | K85: 12546.81
A86: Gislaine Santos | B86: 3040 | C86: 1200 | D86: 1400 | E86: 2560 | F86: 2400 | G86: 1920 | H86: 9480 | K86: 12520
A87: DLOCAL BRASIL INSTITUICAO DE PAGAMENTO S.A. | C87: 2564.19 | D87: 3311.85 | E87: 3098.13 | G87: 3435.73 | H87: 12409.9 | K87: 12409.9
A88: TIMA CONSULTORIA | B88: 12300 | K88: 12300
A89: Gabriel Rocha | B89: 12280 | K89: 12280
A90: PRO-RAD CONSULTORES EM RADIOPROTECAO S/S LTDA | B90: 3571.66 | C90: 1249.06 | D90: 2836.36 | E90: 1498.68 | F90: 1616.68 | G90: 1439.58 | H90: 8640.36 | K90: 12212.02
A91: CAMILO REIS DE AZEVEDO | B91: 12000 | K91: 12000
A92: FR ELEVADORES E PONTES ROLANTES LTDA | D92: 2978.08 | E92: 2964.29 | F92: 2964.29 | G92: 2974.14 | H92: 11880.8 | K92: 11880.8
A93: 60047-MANUTENCAO PREDIAL | D93: 2978.08 | E93: 2964.29 | F93: 2964.29 | G93: 2974.14 | H93: 11880.8 | K93: 11880.8
A94: DJEFFERSON SANTOS DE ARAUJO | B94: 7180 | C94: 1020 | D94: 1080 | E94: 1125 | F94: 1095 | G94: 247.5 | H94: 4567.5 | K94: 11747.5
A95: GENIVALDO DOS SANTOS | B95: 10320 | C95: 600 | G95: 640 | H95: 1240 | K95: 11560
A96: KURT COMERCIO LTDA | B96: 7808 | C96: 650 | D96: 849 | E96: 714 | F96: 828 | G96: 650 | H96: 3691 | K96: 11499
A97: Elaine Da Silva Castro Maciel | B97: 11460 | K97: 11460
A98: Edson Mendonça de Oliveira Junior | B98: 11416.58 | K98: 11416.58
A99: SAPRA LANDAUER SERVICO DE ASSESSORIA E PROTECAO RADIOLOGICA LTDA. | B99: 11402.16 | K99: 11402.16
A100: José Neres | B100: 5680 | C100: 720 | D100: 1008 | E100: 672 | F100: 1428 | G100: 1848 | H100: 5676 | K100: 11356
A101: EVELYN MARTINS FERNANDES DE ARAUJO | B101: 8960 | C101: 1980 | D101: 320 | H101: 2300 | K101: 11260
A102: GUILHERME BOYHER LINO SOUZA | B102: 1036.8 | C102: 1691 | D102: 1978.42 | E102: 2408.9 | F102: 1723 | G102: 2412.38 | H102: 10213.7 | K102: 11250.5
...

Sheet DIN_TAXA
A10: Sum of Pago | B10: Rótulos de Coluna
B11: 2025 | C11: 2026 | H11: 2026 Total | I11: (vazio) | J11: (vazio) Total | K11: Total Geral
C12: jan | D12: fev | E12: mar | F12: abr | G12: mai | I12: <02/01/2025
A13: Rótulos de Linha
A14: 60013-SALARIOS | B14: 457872.8 | C14: 34102 | D14: 34603 | E14: 31312.18 | F14: 32955.08 | G14: 34895.88 | H14: 167868.14 | K14: 625740.94
A15: 60004-INSTRUTOR | B15: 387694.6 | C15: 22440 | D15: 32472 | E15: 25036 | F15: 37714 | G15: 33515 | H15: 151177 | K15: 538871.6
A16: 60040-ALUGUEL | B16: 348243.16 | C16: 27343.18 | D16: 27343.18 | E16: 25123.8 | F16: 28087.8 | G16: 28087.8 | H16: 135985.76 | K16: 484228.92
A17: 60119-SIMPLES NACIONAL | B17: 218627.46 | C17: 20778.97 | D17: 18546.78 | E17: 19708.53 | F17: 18081.14 | G17: 18702.19 | H17: 95817.61 | K17: 314445.07
A18: 60052-ROYALTIES | B18: 204499.04 | C18: 12717.54 | D18: 24839.94 | E18: 20571.58 | F18: 26432.78 | G18: 24737.21 | H18: 109299.05 | K18: 313798.09
A19: 60005-PRECEPTOR | B19: 239003.66 | C19: 12880 | D19: 9860 | E19: 13240 | F19: 16020 | G19: 17580 | H19: 69580 | K19: 308583.66
A20: 60106-JUROS E TAXAS SOBRE EMPRESTIMOS | B20: 191296.46 | C20: 19355.85 | D20: 21052.12 | E20: 21217.11 | F20: 21068.72 | G20: 20788.27 | H20: 103482.07 | K20: 294778.53
A21: 60158-CARTAO DE CREDITO | B21: 214698.17 | C21: 11777.86 | D21: 13409.63 | E21: 12597.71 | F21: 10213.05 | G21: 8683.25 | H21: 56681.5 | K21: 271379.67
A22: 60030-PREMIACOES E GRATIFICACOES | B22: 156787.6 | C22: 10121 | D22: 21688 | E22: 17749 | F22: 17470 | G22: 11303.6 | H22: 78331.6 | K22: 235119.2
A23: 60001-APOSTILA | B23: 155287.22 | C23: 15185.37 | D23: 3152.57 | E23: 12695.6 | F23: 21146.35 | G23: 9342.8 | H23: 61522.69 | K23: 216809.91
A24: 60109-MIDIA DE INTERNET | B24: 146429.73 | C24: 11910.26 | D24: 12041.64 | E24: 12000.93 | F24: 11732.48 | G24: 7546.7 | H24: 55232.01 | K24: 201661.74
A25: 60053-FUNDO DE PROPAGANDA | B25: 133255.14 | C25: 11568.26 | D25: 11802.77 | E25: 12392.42 | F25: 9304.76 | G25: 13742.91 | H25: 58811.12 | K25: 192066.26
... A31: 60159-CONTRA PARTIDA DE ESTAGIO | B31: 35102.06 | C31: 3227.5 | D31: 3527.5 | E31: 9830.59 | F31: 10279.2 | G31: 4055 | H31: 30919.79 | K31: 66021.85
A32: 60067-OUTRAS DESPESAS | B32: 58430.23 | C32: 1413.36 | D32: 405.87 | F32: 524.29 | H32: 2343.52 | K32: 60773.75
A33: 60018-FGTS SALARIO | B33: 34584.1 | C33: 5776.39 | D33: 4717.62 | E33: 4586.75 | F33: 4640.87 | G33: 1473.02 | H33: 21194.65 | K33: 55778.75
A34: 60069-JURIDICO | B34: 21113.06 | C34: 1621 | D34: 9827.92 | E34: 2154.49 | F34: 12509.06 | G34: 3601.34 | H34: 29713.81 | K34: 50826.87
A35: 60003-FARDAMENTO ALUNOS | B35: 31634.47 | C35: 1996.8 | D35: 1567 | E35: 4003.78 | F35: 4646.21 | G35: 5808.67 | H35: 18022.46 | K35: 49656.93
A36: 60047-MANUTENCAO PREDIAL | B36: 23989.36 | C36: 6327 | D36: 4782.58 | E36: 3910.29 | F36: 3708.68 | G36: 4076.43 | H36: 22804.98 | K36: 46794.34
A37: 60098-TARIFAS BANCARIAS | B37: 21692.02 | C37: 4883.76 | D37: 3885.9 | E37: 4547.63 | F37: 4658.27 | G37: 4691.76 | H37: 22667.32 | K37: 44359.34
A38: 60019-RESCISOES / IDENIZACOES | B38: 32648.08 | C38: 1016.14 | D38: 11.26 | E38: 6281.17 | F38: 1600.17 | G38: 2002.16 | H38: 10910.9 | K38: 43558.98
A39: 60017-INSS SALARIO | B39: 29811.73 | C39: 2587.6 | D39: 2614.42 | E39: 2531.11 | F39: 2783.83 | G39: 3101.82 | H39: 13618.78 | K39: 43430.51
A40: 60042-ENERGIA ELETRICA | B40: 14240.77 | C40: 4397.03 | D40: 4645.44 | E40: 4693.61 | F40: 4100.17 | G40: 5096.29 | H40: 22932.54 | K40: 37173.31
A41: 60043-AGUA E ESGOTO | B41: 24046.7 | C41: 2250.53 | D41: 1027.31 | E41: 2455.92 | F41: 1757.08 | G41: 2516.22 | H41: 10007.06 | K41: 34053.76
A42: 60014-FERIAS | B42: 20534.02 | C42: 2243.96 | D42: 1000 | E42: 3318 | F42: 1726.91 | G42: 2245.5 | H42: 10534.37 | K42: 31068.39
A43: 60015-13º SALARIO | B43: 29574.85 | K43: 29574.85
A44: 60068-CONTABILIDADE | B44: 18198.79 | C44: 3060.22 | D44: 1621 | E44: 1628.5 | F44: 1646 | G44: 1621 | H44: 9576.72 | K44: 27775.51
A45: 60027-AJUDA DE CUSTOS PESSOAL | B45: 13980.74 | C45: 1500 | D45: 2535.42 | E45: 1792 | F45: 1859.64 | G45: 1980 | H45: 9667.06 | K45: 23647.8
A46: 60057-MATERIAL DE LIMPEZA E CONSERVACAO | B46: 12129.63 | C46: 1721.21 | D46: 1708.28 | E46: 188.61 | F46: 1818.99 | G46: 2094.25 | H46: 7531.34 | K46: 19660.97
A47: 60078-LOCACAO DE EQUIPAMENTOS | B47: 14960.22 | C47: 390 | D47: 431.59 | E47: 390 | F47: 233.3 | G47: 1174.19 | H47: 2619.08 | K47: 17579.3
A48: 60020-FGTS RESCISORIO | B48: 11898.64 | C48: 2707.76 | E48: 1125.59 | F48: 864.88 | G48: 165.15 | H48: 4863.38 | K48: 16762.02
A49: 60084-OUTRAS CONSULTORIAS | B49: 333 | C49: 2333 | D49: 3331 | E49: 3841.22 | F49: 3044.73 | G49: 3770 | H49: 16319.95 | K49: 16652.95
A50: 60083-TRANSPORTES E FRETES | B50: 9949.81 | C50: 957.55 | D50: 1679.83 | E50: 1000.46 | F50: 1480.37 | G50: 1338.72 | H50: 6456.93 | K50: 16406.74
A51: 60081-SERVICO TECNOLOGIA DA INFORMACAO | B51: 10051 | C51: 900 | D51: 900 | E51: 900 | F51: 900 | G51: 900 | H51: 4500 | K51: 14551
A52: 60049-MANUTENCAO DE EQUIPAMENTOS | B52: 12590.74 | D52: 180 | E52: 99 | F52: 500 | H52: 779 | K52: 13369.74
A53: 60010-DEVOLUCAO DE PARCELAS | B53: 11065.5 | D53: 297.5 | E53: 39.84 | F53: 75 | G53: 11 | H53: 423.34 | K53: 11488.84
A54: 60058-MATERIAL DE USO E CONSUMO | B54: 6524.04 | C54: 485.02 | D54: 108.49 | E54: 1322.35 | F54: 826.86 | G54: 668.27 | H54: 3410.99 | K54: 9935.03
A55: 60045-INTERNET E CONEXOES | B55: 6655 | C55: 605 | D55: 605 | E55: 605 | F55: 605 | G55: 605 | H55: 3025 | K55: 9680
A56: 60039-BOLSA ESTAGIARIOS | B56: 4544.02 | C56: 883.85 | D56: 879.97 | E56: 1159.04 | F56: 1884.97 | G56: 129.97 | H56: 4937.8 | K56: 9481.82
A57: 60008-EQUIPAMENTOS LOCADOS PARA ENSINO | C57: 1249.06 | D57: 2836.36 | E57: 1498.68 | F57: 1616.68 | G57: 1439.58 | H57: 8640.36 | K57: 8640.36
A58: 60048-MANUTENCAO REFRIGERACAO | B58: 4317.96 | C58: 1750 | D58: 358.15 | F58: 1900 | H58: 4008.15 | K58: 8326.11
A59: 60100-TARIFA PIX | B59: 8306.22 | K59: 8306.22
A60: 60091-ESTACIONAMENTO / PEDAGIO | B60: 4673 | C60: 550 | D60: 550 | E60: 550 | F60: 550 | G60: 625 | H60: 2825 | K60: 7498
A61: 60077-IMPRESSOES / COPIAS / CARIMBOS / CARTOES | B61: 7241 | C61: 60 | E61: 6 | H61: 66 | K61: 7307
A62: 60011-DEVOLUCAO DE MATRICULAS | B62: 5489.13 | C62: 387 | D62: 537.48 | E62: 208 | F62: 248 | G62: 69 | H62: 1449.48 | K62: 6938.61
A63: 60102-IOF | B63: 5702.32 | C63: 553.85 | H63: 553.85 | K63: 6256.17
A64: 60054-CONTRIBUICAO ASSOCIATIVA | B64: 4523.86 | C64: 370 | E64: 370 | F64: 377.43 | G64: 370 | H64: 1487.43 | K64: 6011.29
A65: 60037-FARDAMENTO COLABORADORES | B65: 4531.01 | G65: 575.83 | H65: 575.83 | K65: 5106.84
A66: 60007-SEGURO ESTAGIOS | B66: 3341.96 | C66: 217.76 | D66: 217.76 | E66: 217.76 | F66: 217.76 | G66: 222.38 | H66: 1093.42 | K66: 4435.38
A67: 60147-CREDENCIAMENTO NOVOS CURSOS | G67: 3995.68 | H67: 3995.68 | K67: 3995.68
A68: CENTRO ESTADUAL DE EDUCACAO TECNOLOGICA PAULA SOUZA | G68: 3995.68 | H68: 3995.68 | K68: 3995.68
A69: 60021-PENSAO ALIMENTICIA | B69: 3925.98 | K69: 3925.98
A70: 60074-SERVICO DE LIMPEZA | B70: 3178.89 | C70: 280 | F70: 60 | H70: 340 | K70: 3518.89
A71: 70018-REPASSE CAU | C71: 906.32 | D71: 475.32 | E71: 1039.72 | F71: 906.32 | H71: 3327.68 | K71: 3327.68
A72: 60063-FESTAS E CONFRATERNIZACOES | B72: 2407.51 | C72: 204.83 | D72: 19.95 | E72: 127.2 | F72: 28 | G72: 208 | H72: 587.98 | K72: 2995.49
A73: 60055-MATERIAL DE ESCRITORIO | B73: 1098.47 | C73: 103.67 | D73: 2.45 | E73: 334.22 | F73: 412.84 | G73: 973.79 | H73: 1826.97 | K73: 2925.44
A74: 60070-SERVICO DE ANALISE DE CREDITO | B74: 2203.45 | C74: 132 | D74: 142.68 | E74: 139 | F74: 139 | G74: 139 | H74: 691.68 | K74: 2895.13
A75: 60126-INSS (RETIDO) | B75: 2778.9 | K75: 2778.9
A76: 60144-MOVEIS E UTENSILIOS | B76: 2671 | K76: 2671
A77: 70017-MATERIAIS AÇÃO DE SAÚDE/EVENTOS | B77: 307.2 | C77: 41.25 | E77: 186.92 | F77: 1002.39 | G77: 1087.9 | H77: 2318.46 | K77: 2625.66
A78: 60046-TELEFONIA MOVEL | B78: 1640.16 | C78: 85 | D78: 130 | E78: 280 | F78: 40 | G78: 79.25 | H78: 614.25 | K78: 2254.41
A79: 60061-ORNAMENTOS E DECORACOES | B79: 1162.67 | C79: 779.99 | H79: 779.99 | K79: 1942.66
A80: 60089-DESPESAS DE REPRESENTACAO EM VIAGEM | B80: 1852.72 | K80: 1852.72
A81: 60032-EXAMES MEDICOS / PCMSO / PPRA | B81: 1110 | C81: 105 | D81: 35 | E81: 360 | F81: 200 | H81: 700 | K81: 1810
A82: 60002-INSUMOS LABORATORIOS | B82: 1019.92 | D82: 208.92 | E82: 124.98 | F82: 95.79 | G82: 337.07 | H82: 766.76 | K82: 1786.68
A83: 60051-SEGUROS PATRIMONIAIS | B83: 1563.06 | K83: 1563.06
A84: 60082-ASSESSORIA OU CONSULTORIA OPERACIONAL | G84: 1500 | H84: 1500 | K84: 1500
A85: 60034-TREINAMENTOS / CERTIFICADOS | B85: 1250 | E85: 157.8 | H85: 157.8 | K85: 1407.8
A86: 60112-MIDIA DE RADIO | B86: 1365.76 | K86: 1365.76
A87: 70015-TAXA INDICAÇÃO | B87: 950 | C87: 50 | D87: 200 | E87: 50 | F87: 100 | H87: 400 | K87: 1350
A88: 60133-TAXA BOMBEIRO | B88: 1300 | K88: 1300
A89: 60110-MIDIA EXTERNA | B89: 1200 | K89: 1200
A90: 60132-TAXAS MUNICIPAIS | B90: 1140.18 | K90: 1140.18
A91: 60016-IRRF SALARIO | B91: 563.75 | C91: 73.54 | E91: 160.83 | F91: 81.49 | G91: 81.59 | H91: 397.45 | K91: 961.2
A92: 60150-SERVICOS ARQUITETONICOS E PROJETOS | B92: 913 | K92: 913
A93: 60050-SEGURANCA ELETRONICA | B93: 531.92 | C93: 254.44 | H93: 254.44 | K93: 786.36
A94: 60088-ALIMENTACAO EM VIAGEM | B94: 785.14 | K94: 785.14
A95: 60006-BRINDES | B95: 550 | C95: 79 | E95: 37.67 | F95: 90.89 | H95: 207.56 | K95: 757.56
A96: 60071-SERVICO DE POSTAGEM E CORREIOS | B96: 696.63 | K96: 696.63
A97: 60029-BONIFICACOES | B97: 650 | K97: 650
A98: 60056-MATERIAL DE INFORMATICA | B98: 482.16 | D98: 39.9 | G98: 14.07 | H98: 53.97 | K98: 536.13
A99: 70019-CRTR | D99: 466.28 | H99: 466.28 | K99: 466.28
A100: 60033-CONTRIBUICOES ASSOCIATIVAS | D100: 377.46 | H100: 377.46 | K100: 377.46
A101: 60118-MATERIAL GRAFICO | B101: 120.76 | F101: 250.29 | H101: 250.29 | K101: 371.05
A102: 60044-TELEFONE FIXO | E102: 190.47 | G102: 102.52 | H102: 292.99 | K102: 292.99
A103: 60117-BRINDES | B103: 268 | K103: 268
A104: 60087-DESLOCAMENTO EM VIAGENS | B104: 230.91 | K104: 230.91
A105: 60036-EPI'S | B105: 199.98 | K105: 199.98
A106: 60114-EVENTOS / FEIRAS | B106: 141.29 | K106: 141.29
A107: 60097-TARIFA MANUTENCAO DE CONTA | B107: 135.52 | K107: 135.52
A108: 60079-MARCAS / REGISTROS / PATENTES | B108: 125.4 | K108: 125.4
A109: 60131-TAXAS ESTADUAIS | B109: 119.34 | K109: 119.34
A110: 60025-CESTAS BASICAS / CESTAS NATALINAS | B110: 113.74 | K110: 113.74
A111: 60076-CARTORIO | B111: 25.83 | C111: 35.08 | H111: 35.08 | K111: 60.91
A112: 60028-COMISSOES | F112: 50 | H112: 50 | K112: 50
A113: 60059-FERRAMENTAS E ACESSORIOS | B113: 48 | K113: 48
A114: 60060-LIVROS / REVISTAS / JORNAIS | B114: 39.9 | K114: 39.9
...

Sheet BASE
A1: Matrícula | B1: Nome | C1: Taxa | D1: Mês/Ano | E1: Vencimento | F1: Data Baixa | G1: Valor | H1: Juros | I1: Multa | J1: Desconto | K1: Pago | L1: Forma | M1: ANo
A2: 00024 | B2: Google internet ltda | C2: 60109-MIDIA DE INTERNET | D2: 01/2025 | E2: 45659 | F2: 45659 | G2: 1000 | H2: 0 | I2: 0 | J2: 0 | K2: 1000 | L2: Dinheiro | M2: =YEAR(F2) -> 2025
A3: 00248 | B3: Jennifer Franklin Barbosa | C3: 60023-VALE TRANSPORTE | D3: 01/2025 | E3: 45659 | F3: 45659 | G3: 183.6 | H3: 0 | I3: 0 | J3: 0 | K3: 183.6 | L3: Dinheiro | M3: =YEAR(F3) -> 2025
A4: 00315 | B4: HELMA DE SOUSA | C4: 60023-VALE TRANSPORTE | D4: 01/2025 | E4: 45659 | F4: 45659 | G4: 63.6 | H4: 0 | I4: 0 | J4: 0 | K4: 63.6 | L4: Dinheiro | M4: =YEAR(F4) -> 2025
A5: 00193 | B5: FACEBOOK SERVICOS ONLINE DO BR | C5: 60109-MIDIA DE INTERNET | D5: 01/2025 | E5: 45659 | F5: 45659 | G5: 1000 | H5: 0 | I5: 0 | J5: 0 | K5: 1000 | L5: Dinheiro | M5: =YEAR(F5) -> 2025
A6: 00193 | B6: FACEBOOK SERVICOS ONLINE DO BR | C6: 60109-MIDIA DE INTERNET | D6: 01/2025 | E6: 45659 | F6: 45659 | G6: 2288.3 | H6: 0 | I6: 0 | J6: 0 | K6: 2288.3 | L6: Dinheiro | M6: =YEAR(F6) -> 2025
A7: 00024 | B7: Google internet ltda | C7: 60109-MIDIA DE INTERNET | D7: 01/2025 | E7: 45659 | F7: 45659 | G7: 1211.7 | H7: 0 | I7: 0 | J7: 0 | K7: 1211.7 | L7: Dinheiro | M7: =YEAR(F7) -> 2025
A8: 00377 | B8: VIACAO OSASCO LTDA | C8: 60023-VALE TRANSPORTE | D8: 01/2025 | E8: 45659 | F8: 45659 | G8: 165.8 | H8: 0 | I8: 0 | J8: 0 | K8: 165.8 | L8: Dinheiro | M8: =YEAR(F8) -> 2025
A9: 00083 | B9: FLASH BENEFICIOS - VT E VA | C9: 60023-VALE TRANSPORTE | D9: 01/2025 | E9: 45659 | F9: 45659 | G9: 2737.9 | H9: 0 | I9: 0 | J9: 0 | K9: 2737.9 | L9: Dinheiro | M9: =YEAR(F9) -> 2025
A10: 00106 | B10: ALLDIX INFORMATICA LTDA | C10: 60049-MANUTENCAO DE EQUIPAMENTOS | D10: 01/2025 | E10: 45659 | F10: 45659 | G10: 900 | H10: 0 | I10: 0 | J10: 0 | K10: 900 | L10: Dinheiro | M10: =YEAR(F10) -> 2025
A11: 00362 | B11: ITAU UNIBANCO S.A. | C11: 60098-TARIFAS BANCARIAS | D11: 01/2025 | E11: 45660 | F11: 45660 | G11: 1.79 | H11: 0 | I11: 0 | J11: 0 | K11: 1.79 | L11: Dinheiro | M11: =YEAR(F11) -> 2025
A12: 00362 | B12: ITAU UNIBANCO S.A. | C12: 60102-IOF | D12: 01/2025 | E12: 45660 | F12: 45660 | G12: 93.66 | H12: 0 | I12: 0 | J12: 0 | K12: 93.66 | L12: Dinheiro | M12: =YEAR(F12) -> 2025
A13: 00131 | B13: Lorenna Nascimento Santos | C13: 60032-EXAMES MEDICOS / PCMSO / PPRA | D13: 01/2025 | E13: 45660 | F13: 45660 | G13: 30 | H13: 0 | I13: 0 | J13: 0 | K13: 30 | L13: Dinheiro | M13: =YEAR(F13) -> 2025
... A3624: 00316 | B3624: ANE CAROLINA ARAUJO | C3624: 60014-FERIAS | D3624: 12/2025 | E3624: 46009 | F3624: 46009 | G3624: 2245.16 | H3624: 0 | I3624: 0 | J3624: 0 | K3624: 2245.16 | L3624: Dinheiro | M3624: =YEAR(F3624) -> 2025
A3625: 668 | B3625: 62.254.936 SAMIR FARAH | C3625: 60084-OUTRAS CONSULTORIAS | D3625: 45992 | E3625: 46010 | F3625: 46010 | G3625: 333 | H3625: 0 | I3625: 0 | J3625: 0 | K3625: 333 | L3625: Dinheiro | M3625: =YEAR(F3625) -> 2025
A3626: 00351 | B3626: Adriana da Silva Furlan | C3626: 60015-13º SALARIO | D3626: 12/2025 | E3626: 46010 | F3626: 46010 | G3626: 580 | H3626: 0 | I3626: 0 | J3626: 0 | K3626: 580 | L3626: Dinheiro | M3626: =YEAR(F3626) -> 2025
A3627: 00349 | B3627: Marcilene de Jesus Duarte | C3627: 60015-13º SALARIO | D3627: 12/2025 | E3627: 46010 | F3627: 46010 | G3627: 516 | H3627: 0 | I3627: 0 | J3627: 0 | K3627: 516 | L3627: Dinheiro | M3627: =YEAR(F3627) -> 2025
A3628: 00160 | B3628: Cristina Pereira de Sena | C3628: 60015-13º SALARIO | D3628: 12/2025 | E3628: 46010 | F3628: 46010 | G3628: 770 | H3628: 0 | I3628: 0 | J3628: 0 | K3628: 770 | L3628: Dinheiro | M3628: =YEAR(F3628) -> 2025
A3629: 00416 | B3629: Atila Gandhi | C3629: 60015-13º SALARIO | D3629: 12/2025 | E3629: 46010 | F3629: 46010 | G3629: 580 | H3629: 0 | I3629: 0 | J3629: 0 | K3629: 580 | L3629: Dinheiro | M3629: =YEAR(F3629) -> 2025
A3630: 00104 | B3630: DARF | C3630: 60017-INSS SALARIO | D3630: 12/2025 | E3630: 46010 | F3630: 46010 | G3630: 2506.22 | H3630: 0 | I3630: 0 | J3630: 0 | K3630: 2506.22 | L3630: Dinheiro | M3630: =YEAR(F3630) -> 2025
A3631: 00104 | B3631: DARF | C3631: 60017-INSS SALARIO | D3631: 12/2025 | E3631: 46010 | F3631: 46010 | G3631: 2340.96 | H3631: 0 | I3631: 0 | J3631: 0 | K3631: 2340.96 | L3631: Dinheiro | M3631: =YEAR(F3631) -> 2025
A3632: 00104 | B3632: DARF | C3632: 60016-IRRF SALARIO | D3632: 12/2025 | E3632: 46010 | F3632: 46010 | G3632: 74.48 | H3632: 0 | I3632: 0 | J3632: 0 | K3632: 74.48 | L3632: Dinheiro | M3632: =YEAR(F3632) -> 2025
A3633: 00072 | B3633: MINISTERIO DA FAZENDA | C3633: 60119-SIMPLES NACIONAL | D3633: 12/2025 | E3633: 46010 | F3633: 46010 | G3633: 14220.97 | H3633: 0 | I3633: 0 | J3633: 0 | K3633: 14220.97 | L3633: Dinheiro | M3633: =YEAR(F3633) -> 2025
A3634: 00364 | B3634: Naiara Oliveira Rodrigues | C3634: 60015-13º SALARIO | D3634: 12/2025 | E3634: 46010 | F3634: 46010 | G3634: 645 | H3634: 0 | I3634: 0 | J3634: 0 | K3634: 645 | L3634: Dinheiro | M3634: =YEAR(F3634) -> 2025
A3635: 00291 | B3635: Noberto da Silva Ferreira | C3635: 60015-13º SALARIO | D3635: 12/2025 | E3635: 46010 | F3635: 46010 | G3635: 65 | H3635: 0 | I3635: 0 | J3635: 0 | K3635: 65 | L3635: Dinheiro | M3635: =YEAR(F3635) -> 2025
A3636: 00606 | B3636: Priscila de Jesus dos Santos ferreira | C3636: 60015-13º SALARIO | D3636: 12/2025 | E3636: 46010 | F3636: 46010 | G3636: 194 | H3636: 0 | I3636: 0 | J3636: 0 | K3636: 194 | L3636: Dinheiro | M3636: =YEAR(F3636) -> 2025
A3637: 00511 | B3637: Ricardo da Silva Lino | C3637: 60015-13º SALARIO | D3637: 12/2025 | E3637: 46010 | F3637: 46010 | G3637: 638 | H3637: 0 | I3637: 0 | J3637: 0 | K3637: 638 | L3637: Dinheiro | M3637: =YEAR(F3637) -> 2025
... A3692: 00362 | B3692: ITAU UNIBANCO S.A. | C3692: 60158-CARTAO DE CREDITO | D3692: 12/2025 | E3692: 46021 | F3692: 46021 | G3692: 13710.13 | H3692: 0 | I3692: 0 | J3692: 0 | K3692: 1800 | L3692: Banco Investimentos | M3692: =YEAR(F3692) -> 2025
A3693: 154 | B3693: Uber/ frete | C3693: 60083-TRANSPORTES E FRETES | D3693: 46023 | E3693: 46030 | F3693: 46030 | G3693: 47 | H3693: 0 | I3693: 0 | J3693: 0 | K3693: 47 | L3693: Dinheiro | M3693: =YEAR(F3693) -> 2026
A3694: 111 | B3694: Thayna Cristine | C3694: 60030-PREMIACOES E GRATIFICACOES | D3694: 46023 | E3694: 46031 | F3694: 46031 | G3694: 550 | H3694: 0 | I3694: 0 | J3694: 0 | K3694: 550 | L3694: Dinheiro | M3694: =YEAR(F3694) -> 2026
A3695: 331 | B3695: Ricardo Da Silva Lino | C3695: 60030-PREMIACOES E GRATIFICACOES | D3695: 46023 | E3695: 46031 | F3695: 46031 | G3695: 275 | H3695: 0 | I3695: 0 | J3695: 0 | K3695: 275 | L3695: Dinheiro | M3695: =YEAR(F3695) -> 2026
A3696: 398 | B3696: Ana Cristina Pereira | C3696: 60004-INSTRUTOR | D3696: 46023 | E3696: 46032 | F3696: 46035 | G3696: 320 | H3696: 0 | I3696: 0 | J3696: 0 | K3696: 320 | L3696: Dinheiro | M3696: =YEAR(F3696) -> 2026
A3697: 409 | B3697: Ryan Miguel Novaes dos Santos | C3697: 60023-VALE TRANSPORTE | D3697: 46023 | E3697: 46042 | F3697: 46042 | G3697: 240 | H3697: 0 | I3697: 0 | J3697: 0 | K3697: 240 | L3697: Dinheiro | M3697: =YEAR(F3697) -> 2026
A3698: 00039 | B3698: Barkev Materiais de Construções LTDA | C3698: 60047-MANUTENCAO PREDIAL | D3698: 01/2026 | E3698: 46024 | F3698: 46024 | G3698: 42 | H3698: 0 | I3698: 0 | J3698: 0 | K3698: 42 | L3698: Dinheiro | M3698: =YEAR(F3698) -> 2026
A3699: 00663 | B3699: MARIA PAULA DA SILVA SOUSA | C3699: 60023-VALE TRANSPORTE | D3699: 01/2026 | E3699: 46024 | F3699: 46024 | G3699: 11 | H3699: 0 | I3699: 0 | J3699: 0 | K3699: 11 | L3699: Dinheiro | M3699: =YEAR(F3699) -> 2026
A3700: 00039 | B3700: Barkev Materiais de Construções LTDA | C3700: 60047-MANUTENCAO PREDIAL | D3700: 01/2026 | E3700: 46027 | F3700: 46027 | G3700: 48.7 | H3700: 0 | I3700: 0 | J3700: 0 | K3700: 48.7 | L3700: Dinheiro | M3700: =YEAR(F3700) -> 2026
A3701: 00613 | B3701: JULIANA MARIA VICENTE BOTELHO | C3701: 60030-PREMIACOES E GRATIFICACOES | D3701: 01/2026 | E3701: 46027 | F3701: 46027 | G3701: 40 | H3701: 0 | I3701: 0 | J3701: 0 | K3701: 40 | L3701: Dinheiro | M3701: =YEAR(F3701) -> 2026
A3702: 00364 | B3702: Naiara Oliveira Rodrigues | C3702: 60030-PREMIACOES E GRATIFICACOES | D3702: 01/2026 | E3702: 46027 | F3702: 46027 | G3702: 66 | H3702: 0 | I3702: 0 | J3702: 0 | K3702: 66 | L3702: Dinheiro | M3702: =YEAR(F3702) -> 2026
A3703: 00467 | B3703: Chavelândia | C3703: 60077-IMPRESSOES / COPIAS / CARIMBOS / CARTOES | D3703: 01/2026 | E3703: 46028 | F3703: 46028 | G3703: 12 | H3703: 0 | I3703: 0 | J3703: 0 | K3703: 12 | L3703: Dinheiro | M3703: =YEAR(F3703) -> 2026
A3704: 00036 | B3704: Casulo Destribuidora de Doces LDTA | C3704: 60063-FESTAS E CONFRATERNIZACOES | D3704: 01/2026 | E3704: 46028 | F3704: 46028 | G3704: 13.99 | H3704: 0 | I3704: 0 | J3704: 0 | K3704: 13.99 | L3704: Dinheiro | M3704: =YEAR(F3704) -> 2026
A3705: 00292 | B3705: Psicomed S/C LTDA | C3705: 60032-EXAMES MEDICOS / PCMSO / PPRA | D3705: 01/2026 | E3705: 46028 | F3705: 46028 | G3705: 35 | H3705: 0 | I3705: 0 | J3705: 0 | K3705: 35 | L3705: Dinheiro | M3705: =YEAR(F3705) -> 2026
A3706: 00027 | B3706: EXTRA Cia Brasileira de distribuição | C3706: 60058-MATERIAL DE USO E CONSUMO | D3706: 01/2026 | E3706: 46028 | F3706: 46028 | G3706: 14.47 | H3706: 0 | I3706: 0 | J3706: 0 | K3706: 14.47 | L3706: Dinheiro | M3706: =YEAR(F3706) -> 2026
A3707: 00032 | B3707: ARMARINHOS FERNANDO LTDA | C3707: 60055-MATERIAL DE ESCRITORIO | D3707: 01/2026 | E3707: 46028 | F3707: 46028 | G3707: 26.97 | H3707: 0 | I3707: 0 | J3707: 0 | K3707: 26.97 | L3707: Dinheiro | M3707: =YEAR(F3707) -> 2026
A3708: 00536 | B3708: RECEITA FEDERAL | C3708: 60076-CARTORIO | D3708: 01/2026 | E3708: 46028 | F3708: 46028 | G3708: 8.61 | H3708: 0 | I3708: 0 | J3708: 0 | K3708: 8.61 | L3708: Dinheiro | M3708: =YEAR(F3708) -> 2026
A3709: 00403 | B3709: FABRICIO MARCELO SANTOS RODRIG | C3709: 60047-MANUTENCAO PREDIAL | D3709: 01/2026 | E3709: 46024 | F3709: 46028 | G3709: 200 | H3709: 0 | I3709: 0 | J3709: 0 | K3709: 200 | L3709: Dinheiro | M3709: =YEAR(F3709) -> 2026
... A4398: 00255 | B4398: Banca da Alice | C4398: 60046-TELEFONIA MOVEL | D4398: 03/2026 | E4398: 46111 | F4398: 46111 | G4398: 30 | H4398: 0 | I4398: 0 | J4398: 0 | K4398: 30 | L4398: Dinheiro | M4398: =YEAR(F4398) -> 2026
A4399: 00722 | B4399: Bruno Meireles Leme | C4399: 70008-JALECO G | D4399: 03/2026 | E4399: 46112 | F4399: 46112 | G4399: 0 | K4399: 0 | L4399: Dinheiro | M4399: =YEAR(F4399) -> 2026
A4400: 00160 | B4400: Cristina Pereira de Sena | C4400: 60023-VALE TRANSPORTE | D4400: 03/2026 | E4400: 46083 | F4400: 46083 | G4400: 317.2 | H4400: 0 | I4400: 0 | J4400: 0 | K4400: 317.2 | L4400: Dinheiro | M4400: =YEAR(F4400) -> 2026
A4401: 00160 | B4401: Cristina Pereira de Sena | C4401: 60022-VALE ALIMENTACAO / REFEICAO | D4401: 03/2026 | E4401: 46083 | F4401: 46083 | G4401: 255.42 | H4401: 0 | I4401: 0 | J4401: 0 | K4401: 255.42 | L4401: Dinheiro | M4401: =YEAR(F4401) -> 2026
A4402: 00474 | B4402: Henrique Lima Martins Lares | C4402: 60023-VALE TRANSPORTE | D4402: 03/2026 | E4402: 46083 | F4402: 46083 | G4402: 231.8 | H4402: 0 | I4402: 0 | J4402: 0 | K4402: 231.8 | L4402: Dinheiro | M4402: =YEAR(F4402) -> 2026
A4403: 00474 | B4403: Henrique Lima Martins Lares | C4403: 60022-VALE ALIMENTACAO / REFEICAO | D4403: 03/2026 | E4403: 46083 | F4403: 46083 | G4403: 255.42 | H4403: 0 | I4403: 0 | J4403: 0 | K4403: 255.42 | L4403: Dinheiro | M4403: =YEAR(F4403) -> 2026
A4404: 00411 | B4404: Maria Lucia F. da Cunha | C4404: 60023-VALE TRANSPORTE | D4404: 03/2026 | E4404: 46083 | F4404: 46083 | G4404: 280.6 | H4404: 0 | I4404: 0 | J4404: 0 | K4404: 280.6 | L4404: Dinheiro | M4404: =YEAR(F4404) -> 2026
A4405: 00411 | B4405: Maria Lucia F. da Cunha | C4405: 60022-VALE ALIMENTACAO / REFEICAO | D4405: 03/2026 | E4405: 46083 | F4405: 46083 | G4405: 255.42 | H4405: 0 | I4405: 0 | J4405: 0 | K4405: 255.42 | L4405: Dinheiro | M4405: =YEAR(F4405) -> 2026
A4406: 00349 | B4406: Marcilene de Jesus Duarte | C4406: 60023-VALE TRANSPORTE | D4406: 03/2026 | E4406: 46083 | F4406: 46083 | G4406: 546 | H4406: 0 | I4406: 0 | J4406: 0 | K4406: 546 | L4406: Dinheiro | M4406: =YEAR(F4406) -> 2026
A4407: 00349 | B4407: Marcilene de Jesus Duarte | C4407: 60022-VALE ALIMENTACAO / REFEICAO | D4407: 03/2026 | E4407: 46083 | F4407: 46083 | G4407: 255.42 | H4407: 0 | I4407: 0 | J4407: 0 | K4407: 255.42 | L4407: Dinheiro | M4407: =YEAR(F4407) -> 2026
A4408: 00464 | B4408: Victor Tavares Vian | C4408: 60023-VALE TRANSPORTE | D4408: 03/2026 | E4408: 46083 | F4408: 46083 | G4408: 256.2 | H4408: 0 | I4408: 0 | J4408: 0 | K4408: 256.2 | L4408: Dinheiro | M4408: =YEAR(F4408) -> 2026
A4409: 00502 | B4409: João Victor Santos Costa | C4409: 60023-VALE TRANSPORTE | D4409: 03/2026 | E4409: 46083 | F4409: 46083 | G4409: 412.72 | H4409: 0 | I4409: 0 | J4409: 0 | K4409: 412.72 | L4409: Dinheiro | M4409: =YEAR(F4409) -> 2026
A4410: 00502 | B4410: João Victor Santos Costa | C4410: 60022-VALE ALIMENTACAO / REFEICAO | D4410: 03/2026 | E4410: 46083 | F4410: 46083 | G4410: 255.42 | H4410: 0 | I4410: 0 | J4410: 0 | K4410: 255.42 | L4410: Dinheiro | M4410: =YEAR(F4410) -> 2026
A4411: 00168 | B4411: Thayna Cristine | C4411: 60023-VALE TRANSPORTE | D4411: 03/2026 | E4411: 46083 | F4411: 46083 | G4411: 452.8 | H4411: 0 | I4411: 0 | J4411: 0 | K4411: 452.8 | L4411: Dinheiro | M4411: =YEAR(F4411) -> 2026
... A5339: 00732 | B5339: TRIBUNAL REGIONAL DO TRABALHO DA 2A REGIAO | C5339: 60069-JURIDICO | D5339: 05/2026 | E5339: 46167 | F5339: 46168 | G5339: 990.17 | H5339: 0 | I5339: 0 | J5339: 0 | K5339: 990.17 | L5339: Dinheiro | M5339: =YEAR(F5339) -> 2026

Sheet REAL_X_ORC_MAIO
A1: COMPARATIVO REAL x ORÇADO - MAIO/2026 | H1: 🔄 Dados vinculados à DIN_TAXA - ATUALIZAÇÃO AUTOMÁTICA
A2: TOTAL | C2: =SUM(C4:C107) -> 325529.15 | D2: =SUM(D4:D107) -> 333682.87 | E2: =D2-C2 -> 8153.7233 | F2: =IF(C2=0,0,(D2-C2)/C2) -> 0.025047598 | H2: 46168
A3: Despesa | C3: Orçado (Mai) | D3: Real (Mai) | E3: Diferença | F3: Var % | H3: 📊 RESUMO
A4: 60004-INSTRUTOR | C4: =IFERROR(VLOOKUP(A4,PROJECAO_2026!$A$4:$F$120,6,FALSE),0) -> 35000 | D4: =IFERROR(VLOOKUP(A4,DIN_TAXA!$A$14:$G$121,7,FALSE),0) -> 33515 | E4: =D4-C4 -> -1485 | F4: =IF(C4=0,IF(D4=0,"0%","N/A"),TEXT((D4-C4)/C4,"0%")) -> -4% | H4: Orçado Maio: | I4: =C2 -> 325529.15
A5: 60013-SALARIOS | C5: =IFERROR(VLOOKUP(A5,PROJECAO_2026!$A$4:$F$120,6,FALSE),0) -> 33243.065 | D5: =IFERROR(VLOOKUP(A5,DIN_TAXA!$A$14:$G$121,7,FALSE),0) -> 34895.88 | E5: =D5-C5 -> 1652.815 | F5: =IF(C5=0,IF(D5=0,"0%","N/A"),TEXT((D5-C5)/C5,"0%")) -> 5% | H5: Real Maio: | I5: =D2 -> 333682.87
A6: 60040-ALUGUEL | C6: =IFERROR(VLOOKUP(A6,PROJECAO_2026!$A$4:$F$120,6,FALSE),0) -> 28087.8 | D6: =IFERROR(VLOOKUP(A6,DIN_TAXA!$A$14:$G$121,7,FALSE),0) -> 28087.8 | E6: =D6-C6 -> 0 | F6: =IF(C6=0,IF(D6=0,"0%","N/A"),TEXT((D6-C6)/C6,"0%")) -> 0% | H6: % Executado: | I6: =IF(C2=0,0,D2/C2) -> 1.0250476
A7: 60106-JUROS E TAXAS SOBRE EMPRESTIMOS | C7: =IFERROR(VLOOKUP(A7,PROJECAO_2026!$A$4:$F$120,6,FALSE),0) -> 20541.693 | D7: =IFERROR(VLOOKUP(A7,DIN_TAXA!$A$14:$G$121,7,FALSE),0) -> 20788.27 | E7: =D7-C7 -> 246.57667 | F7: =IF(C7=0,IF(D7=0,"0%","N/A"),TEXT((D7-C7)/C7,"0%")) -> 1% | H7: Saldo a Pagar: | I7: =C2-D2 -> -8153.7233
A8: 60119-SIMPLES NACIONAL | C8: =IFERROR(VLOOKUP(A8,PROJECAO_2026!$A$4:$F$120,6,FALSE),0) -> 19678.093 | D8: =IFERROR(VLOOKUP(A8,DIN_TAXA!$A$14:$G$121,7,FALSE),0) -> 18702.19 | E8: =D8-C8 -> -975.90333 | F8: =IF(C8=0,IF(D8=0,"0%","N/A"),TEXT((D8-C8)/C8,"0%")) -> -5%
A9: 60052-ROYALTIES | C9: =IFERROR(VLOOKUP(A9,PROJECAO_2026!$A$4:$F$120,6,FALSE),0) -> 22000 | D9: =IFERROR(VLOOKUP(A9,DIN_TAXA!$A$14:$G$121,7,FALSE),0) -> 24737.21 | E9: =D9-C9 -> 2737.21 | F9: =IF(C9=0,IF(D9=0,"0%","N/A"),TEXT((D9-C9)/C9,"0%")) -> 12% | H9: 🔴 CONTAS MAIS ESTOURADAS (Diferença ≥ R$ 1.000)
A10: 60030-PREMIACOES E GRATIFICACOES | C10: =IFERROR(VLOOKUP(A10,PROJECAO_2026!$A$4:$F$120,6,FALSE),0) -> 12000 | D10: =IFERROR(VLOOKUP(A10,DIN_TAXA!$A$14:$G$121,7,FALSE),0) -> 11303.6 | E10: =D10-C10 -> -696.4 | F10: =IF(C10=0,IF(D10=0,"0%","N/A"),TEXT((D10-C10)/C10,"0%")) -> -6% | H10: Despesa | I10: Orçado | J10: Real | K10: Diferença | L10: Var %
A11: 60005-PRECEPTOR | C11: =IFERROR(VLOOKUP(A11,PROJECAO_2026!$A$4:$F$120,6,FALSE),0) -> 16000 | D11: =IFERROR(VLOOKUP(A11,DIN_TAXA!$A$14:$G$121,7,FALSE),0) -> 17580 | E11: =D11-C11 -> 1580 | F11: =IF(C11=0,IF(D11=0,"0%","N/A"),TEXT((D11-C11)/C11,"0%")) -> 10% | H11: {=IFERROR(INDEX($A$4:$A$107,MATCH(LARGE(IF($E$4:$E$107>=1000,$E$4:$E$107),1),$E$4:$E$107,0)),"")} -> 60147-CREDENCIAMENTO NOVOS CURSOS | I11: =IFERROR(VLOOKUP(H11,$A$4:$C$107,3,FALSE),0) -> 0 | J11: =IFERROR(VLOOKUP(H11,$A$4:$D$107,4,FALSE),0) -> 3995.68 | K11: =IFERROR(VLOOKUP(H11,$A$4:$E$107,5,FALSE),0) -> 3995.68 | L11: =IFERROR(VLOOKUP(H11,$A$4:$F$107,6,FALSE),"-") -> N/A
A12: 60158-CARTAO DE CREDITO | C12: =IFERROR(VLOOKUP(A12,PROJECAO_2026!$A$4:$F$120,6,FALSE),0) -> 10500 | D12: =IFERROR(VLOOKUP(A12,DIN_TAXA!$A$14:$G$121,7,FALSE),0) -> 8683.25 | E12: =D12-C12 -> -1816.75 | F12: =IF(C12=0,IF(D12=0,"0%","N/A"),TEXT((D12-C12)/C12,"0%")) -> -17% | H12: {=IFERROR(INDEX($A$4:$A$107,MATCH(LARGE(IF($E$4:$E$107>=1000,$E$4:$E$107),2),$E$4:$E$107,0)),"")} -> 60003-FARDAMENTO ALUNOS | I12: =IFERROR(VLOOKUP(H12,$A$4:$C$107,3,FALSE),0) -> 2522.5267 | J12: =IFERROR(VLOOKUP(H12,$A$4:$D$107,4,FALSE),0) -> 5808.67 | K12: =IFERROR(VLOOKUP(H12,$A$4:$E$107,5,FALSE),0) -> 3286.1433 | L12: =IFERROR(VLOOKUP(H12,$A$4:$F$107,6,FALSE),"-") -> 130%
A13: 60012-PRO LABORE | C13: =IFERROR(VLOOKUP(A13,PROJECAO_2026!$A$4:$F$120,6,FALSE),0) -> 12000 | D13: =IFERROR(VLOOKUP(A13,DIN_TAXA!$A$14:$G$121,7,FALSE),0) -> 12000 | E13: =D13-C13 -> 0 | F13: =IF(C13=0,IF(D13=0,"0%","N/A"),TEXT((D13-C13)/C13,"0%")) -> 0% | H13: {=IFERROR(INDEX($A$4:$A$107,MATCH(LARGE(IF($E$4:$E$107>=1000,$E$4:$E$107),3),$E$4:$E$107,0)),"")} -> 60052-ROYALTIES | I13: =IFERROR(VLOOKUP(H13,$A$4:$C$107,3,FALSE),0) -> 22000 | J13: =IFERROR(VLOOKUP(H13,$A$4:$D$107,4,FALSE),0) -> 24737.21 | K13: =IFERROR(VLOOKUP(H13,$A$4:$E$107,5,FALSE),0) -> 2737.21 | L13: =IFERROR(VLOOKUP(H13,$A$4:$F$107,6,FALSE),"-") -> 12%
A14: 60109-MIDIA DE INTERNET | C14: =IFERROR(VLOOKUP(A14,PROJECAO_2026!$A$4:$F$120,6,FALSE),0) -> 11984.277 | D14: =IFERROR(VLOOKUP(A14,DIN_TAXA!$A$14:$G$121,7,FALSE),0) -> 7546.7 | E14: =D14-C14 -> -4437.5767 | F14: =IF(C14=0,IF(D14=0,"0%","N/A"),TEXT((D14-C14)/C14,"0%")) -> -37% | H14: {=IFERROR(INDEX($A$4:$A$107,MATCH(LARGE(IF($E$4:$E$107>=1000,$E$4:$E$107),4),$E$4:$E$107,0)),"")} -> 60069-JURIDICO | I14: =IFERROR(VLOOKUP(H14,$A$4:$C$107,3,FALSE),0) -> 1621 | J14: =IFERROR(VLOOKUP(H14,$A$4:$D$107,4,FALSE),0) -> 3601.34 | K14: =IFERROR(VLOOKUP(H14,$A$4:$E$107,5,FALSE),0) -> 1980.34 | L14: =IFERROR(VLOOKUP(H14,$A$4:$F$107,6,FALSE),"-") -> 122%
A15: 60053-FUNDO DE PROPAGANDA | C15: =IFERROR(VLOOKUP(A15,PROJECAO_2026!$A$4:$F$120,6,FALSE),0) -> 11921.15 | D15: =IFERROR(VLOOKUP(A15,DIN_TAXA!$A$14:$G$121,7,FALSE),0) -> 13742.91 | E15: =D15-C15 -> 1821.76 | F15: =IF(C15=0,IF(D15=0,"0%","N/A"),TEXT((D15-C15)/C15,"0%")) -> 15% | H15: {=IFERROR(INDEX($A$4:$A$107,MATCH(LARGE(IF($E$4:$E$107>=1000,$E$4:$E$107),5),$E$4:$E$107,0)),"")} -> 60053-FUNDO DE PROPAGANDA | I15: =IFERROR(VLOOKUP(H15,$A$4:$C$107,3,FALSE),0) -> 11921.15 | J15: =IFERROR(VLOOKUP(H15,$A$4:$D$107,4,FALSE),0) -> 13742.91 | K15: =IFERROR(VLOOKUP(H15,$A$4:$E$107,5,FALSE),0) -> 1821.76 | L15: =IFERROR(VLOOKUP(H15,$A$4:$F$107,6,FALSE),"-") -> 15%
A16: 60001-APOSTILA | C16: =IFERROR(VLOOKUP(A16,PROJECAO_2026!$A$4:$F$120,6,FALSE),0) -> 10344.513 | D16: =IFERROR(VLOOKUP(A16,DIN_TAXA!$A$14:$G$121,7,FALSE),0) -> 9342.8 | E16: =D16-C16 -> -1001.7133 | F16: =IF(C16=0,IF(D16=0,"0%","N/A"),TEXT((D16-C16)/C16,"0%")) -> -10% | H16: {=IFERROR(INDEX($A$4:$A$107,MATCH(LARGE(IF($E$4:$E$107>=1000,$E$4:$E$107),6),$E$4:$E$107,0)),"")} -> 60013-SALARIOS | I16: =IFERROR(VLOOKUP(H16,$A$4:$C$107,3,FALSE),0) -> 33243.065 | J16: =IFERROR(VLOOKUP(H16,$A$4:$D$107,4,FALSE),0) -> 34895.88 | K16: =IFERROR(VLOOKUP(H16,$A$4:$E$107,5,FALSE),0) -> 1652.815 | L16: =IFERROR(VLOOKUP(H16,$A$4:$F$107,6,FALSE),"-") -> 5%
A17: 60023-VALE TRANSPORTE | C17: =IFERROR(VLOOKUP(A17,PROJECAO_2026!$A$4:$F$120,6,FALSE),0) -> 9618.0533 | D17: =IFERROR(VLOOKUP(A17,DIN_TAXA!$A$14:$G$121,7,FALSE),0) -> 9140.26 | E17: =D17-C17 -> -477.79333 | F17: =IF(C17=0,IF(D17=0,"0%","N/A"),TEXT((D17-C17)/C17,"0%")) -> -5% | H17: {=IFERROR(INDEX($A$4:$A$107,MATCH(LARGE(IF($E$4:$E$107>=1000,$E$4:$E$107),7),$E$4:$E$107,0)),"")} -> 60005-PRECEPTOR | I17: =IFERROR(VLOOKUP(H17,$A$4:$C$107,3,FALSE),0) -> 16000 | J17: =IFERROR(VLOOKUP(H17,$A$4:$D$107,4,FALSE),0) -> 17580 | K17: =IFERROR(VLOOKUP(H17,$A$4:$E$107,5,FALSE),0) -> 1580 | L17: =IFERROR(VLOOKUP(H17,$A$4:$F$107,6,FALSE),"-") -> 10%
A18: 60009-SERVICOS DE ASSESSORIA PEDAGOGICA | C18: =IFERROR(VLOOKUP(A18,PROJECAO_2026!$A$4:$F$120,6,FALSE),0) -> 8076 | D18: =IFERROR(VLOOKUP(A18,DIN_TAXA!$A$14:$G$121,7,FALSE),0) -> 8798 | E18: =D18-C18 -> 722 | F18: =IF(C18=0,IF(D18=0,"0%","N/A"),TEXT((D18-C18)/C18,"0%")) -> 9% | H18: {=IFERROR(INDEX($A$4:$A$107,MATCH(LARGE(IF($E$4:$E$107>=1000,$E$4:$E$107),8),$E$4:$E$107,0)),"")} -> 60082-ASSESSORIA OU CONSULTORIA OPERACIONAL | I18: =IFERROR(VLOOKUP(H18,$A$4:$C$107,3,FALSE),0) -> 0 | J18: =IFERROR(VLOOKUP(H18,$A$4:$D$107,4,FALSE),0) -> 1500 | K18: =IFERROR(VLOOKUP(H18,$A$4:$E$107,5,FALSE),0) -> 1500 | L18: =IFERROR(VLOOKUP(H18,$A$4:$F$107,6,FALSE),"-") -> N/A
A19: 60159-CONTRA PARTIDA DE ESTAGIO | C19: =IFERROR(VLOOKUP(A19,PROJECAO_2026!$A$4:$F$120,6,FALSE),0) -> 3500 | D19: =IFERROR(VLOOKUP(A19,DIN_TAXA!$A$14:$G$121,7,FALSE),0) -> 4055 | E19: =D19-C19 -> 555 | F19: =IF(C19=0,IF(D19=0,"0%","N/A"),TEXT((D19-C19)/C19,"0%")) -> 16% | H19: {=IFERROR(INDEX($A$4:$A$107,MATCH(LARGE(IF($E$4:$E$107>=1000,$E$4:$E$107),9),$E$4:$E$107,0)),"")} -> 70017-MATERIAIS AÇÃO DE SAÚDE/EVENTOS | I19: =IFERROR(VLOOKUP(H19,$A$4:$C$107,3,FALSE),0) -> 76.056667 | J19: =IFERROR(VLOOKUP(H19,$A$4:$D$107,4,FALSE),0) -> 1087.9 | K19: =IFERROR(VLOOKUP(H19,$A$4:$E$107,5,FALSE),0) -> 1011.8433 | L19: =IFERROR(VLOOKUP(H19,$A$4:$F$107,6,FALSE),"-") -> 1330%
A20: 60022-VALE ALIMENTACAO / REFEICAO | C20: =IFERROR(VLOOKUP(A20,PROJECAO_2026!$A$4:$F$120,6,FALSE),0) -> 5311.5633 | D20: =IFERROR(VLOOKUP(A20,DIN_TAXA!$A$14:$G$121,7,FALSE),0) -> 5858.22 | E20: =D20-C20 -> 546.65667 | F20: =IF(C20=0,IF(D20=0,"0%","N/A"),TEXT((D20-C20)/C20,"0%")) -> 10% | H20: TOTAL ESTOUROS | I20: =SUM(I11:I19) -> 87383.798 | J20: =SUM(J11:J19) -> 106949.59 | K20: =SUM(K11:K19) -> 19565.792 | L20: -
A21: 60018-FGTS SALARIO | C21: =IFERROR(VLOOKUP(A21,PROJECAO_2026!$A$4:$F$120,6,FALSE),0) -> 5026.92 | D21: =IFERROR(VLOOKUP(A21,DIN_TAXA!$A$14:$G$121,7,FALSE),0) -> 1473.02 | E21: =D21-C21 -> -3553.9 | F21: =IF(C21=0,IF(D21=0,"0%","N/A"),TEXT((D21-C21)/C21,"0%")) -> -71% | H21: 🟢 CONTAS COM MAIOR ECONOMIA (Diferença ≤ -R$ 1.000)
A22: 60047-MANUTENCAO PREDIAL | C22: =IFERROR(VLOOKUP(A22,PROJECAO_2026!$A$4:$F$120,6,FALSE),0) -> 3809.485 | D22: =IFERROR(VLOOKUP(A22,DIN_TAXA!$A$14:$G$121,7,FALSE),0) -> 4076.43 | E22: =D22-C22 -> 266.945 | F22: =IF(C22=0,IF(D22=0,"0%","N/A"),TEXT((D22-C22)/C22,"0%")) -> 7% | H22: Despesa | I22: Orçado | J22: Real | K22: Economia | L22: Var %
A23: 60042-ENERGIA ELETRICA | C23: =IFERROR(VLOOKUP(A23,PROJECAO_2026!$A$4:$F$120,6,FALSE),0) -> 4578.6933 | D23: =IFERROR(VLOOKUP(A23,DIN_TAXA!$A$14:$G$121,7,FALSE),0) -> 5096.29 | E23: =D23-C23 -> 517.59667 | F23: =IF(C23=0,IF(D23=0,"0%","N/A"),TEXT((D23-C23)/C23,"0%")) -> 11% | H23: {=IFERROR(INDEX($A$4:$A$107,MATCH(SMALL(IF($E$4:$E$107<=-1000,$E$4:$E$107),1),$E$4:$E$107,0)),"")} -> 60109-MIDIA DE INTERNET | I23: =IFERROR(VLOOKUP(H23,$A$4:$C$107,3,FALSE),0) -> 11984.277 | J23: =IFERROR(VLOOKUP(H23,$A$4:$D$107,4,FALSE),0) -> 7546.7 | K23: =IFERROR(VLOOKUP(H23,$A$4:$E$107,5,FALSE),0) -> -4437.5767 | L23: =IFERROR(VLOOKUP(H23,$A$4:$F$107,6,FALSE),"-") -> -37%
A24: 60098-TARIFAS BANCARIAS | C24: =IFERROR(VLOOKUP(A24,PROJECAO_2026!$A$4:$F$120,6,FALSE),0) -> 4439.0967 | D24: =IFERROR(VLOOKUP(A24,DIN_TAXA!$A$14:$G$121,7,FALSE),0) -> 4691.76 | E24: =D24-C24 -> 252.66333 | F24: =IF(C24=0,IF(D24=0,"0%","N/A"),TEXT((D24-C24)/C24,"0%")) -> 6% | H24: {=IFERROR(INDEX($A$4:$A$107,MATCH(SMALL(IF($E$4:$E$107<=-1000,$E$4:$E$107),2),$E$4:$E$107,0)),"")} -> 60018-FGTS SALARIO | I24: =IFERROR(VLOOKUP(H24,$A$4:$C$107,3,FALSE),0) -> 5026.92 | J24: =IFERROR(VLOOKUP(H24,$A$4:$D$107,4,FALSE),0) -> 1473.02 | K24: =IFERROR(VLOOKUP(H24,$A$4:$E$107,5,FALSE),0) -> -3553.9 | L24: =IFERROR(VLOOKUP(H24,$A$4:$F$107,6,FALSE),"-") -> -71%
A25: 60080-ALUGUEL / ASSINATURA DE SISTEMAS | C25: =IFERROR(VLOOKUP(A25,PROJECAO_2026!$A$4:$F$120,6,FALSE),0) -> 4058.85 | D25: =IFERROR(VLOOKUP(A25,DIN_TAXA!$A$14:$G$121,7,FALSE),0) -> 4014.36 | E25: =D25-C25 -> -44.49 | F25: =IF(C25=0,IF(D25=0,"0%","N/A"),TEXT((D25-C25)/C25,"0%")) -> -1% | H25: {=IFERROR(INDEX($A$4:$A$107,MATCH(SMALL(IF($E$4:$E$107<=-1000,$E$4:$E$107),3),$E$4:$E$107,0)),"")} -> 60158-CARTAO DE CREDITO | I25: =IFERROR(VLOOKUP(H25,$A$4:$C$107,3,FALSE),0) -> 10500 | J25: =IFERROR(VLOOKUP(H25,$A$4:$D$107,4,FALSE),0) -> 8683.25 | K25: =IFERROR(VLOOKUP(H25,$A$4:$E$107,5,FALSE),0) -> -1816.75 | L25: =IFERROR(VLOOKUP(H25,$A$4:$F$107,6,FALSE),"-") -> -17%
A26: 60084-OUTRAS CONSULTORIAS | C26: =IFERROR(VLOOKUP(A26,PROJECAO_2026!$A$4:$F$120,6,FALSE),0) -> 3168.4067 | D26: =IFERROR(VLOOKUP(A26,DIN_TAXA!$A$14:$G$121,7,FALSE),0) -> 3770 | E26: =D26-C26 -> 601.59333 | F26: =IF(C26=0,IF(D26=0,"0%","N/A"),TEXT((D26-C26)/C26,"0%")) -> 19% | H26: {=IFERROR(INDEX($A$4:$A$107,MATCH(SMALL(IF($E$4:$E$107<=-1000,$E$4:$E$107),4),$E$4:$E$107,0)),"")} -> 60004-INSTRUTOR | I26: =IFERROR(VLOOKUP(H26,$A$4:$C$107,3,FALSE),0) -> 35000 | J26: =IFERROR(VLOOKUP(H26,$A$4:$D$107,4,FALSE),0) -> 33515 | K26: =IFERROR(VLOOKUP(H26,$A$4:$E$107,5,FALSE),0) -> -1485 | L26: =IFERROR(VLOOKUP(H26,$A$4:$F$107,6,FALSE),"-") -> -4%
A27: 60017-INSS SALARIO | C27: =IFERROR(VLOOKUP(A27,PROJECAO_2026!$A$4:$F$120,6,FALSE),0) -> 2577.71 | D27: =IFERROR(VLOOKUP(A27,DIN_TAXA!$A$14:$G$121,7,FALSE),0) -> 3101.82 | E27: =D27-C27 -> 524.11 | F27: =IF(C27=0,IF(D27=0,"0%","N/A"),TEXT((D27-C27)/C27,"0%")) -> 20% | H27: {=IFERROR(INDEX($A$4:$A$107,MATCH(SMALL(IF($E$4:$E$107<=-1000,$E$4:$E$107),5),$E$4:$E$107,0)),"")} -> 60001-APOSTILA | I27: =IFERROR(VLOOKUP(H27,$A$4:$C$107,3,FALSE),0) -> 10344.513 | J27: =IFERROR(VLOOKUP(H27,$A$4:$D$107,4,FALSE),0) -> 9342.8 | K27: =IFERROR(VLOOKUP(H27,$A$4:$E$107,5,FALSE),0) -> -1001.7133 | L27: =IFERROR(VLOOKUP(H27,$A$4:$F$107,6,FALSE),"-") -> -10%
A28: 60003-FARDAMENTO ALUNOS | C28: =IFERROR(VLOOKUP(A28,PROJECAO_2026!$A$4:$F$120,6,FALSE),0) -> 2522.5267 | D28: =IFERROR(VLOOKUP(A28,DIN_TAXA!$A$14:$G$121,7,FALSE),0) -> 5808.67 | E28: =D28-C28 -> 3286.1433 | F28: =IF(C28=0,IF(D28=0,"0%","N/A"),TEXT((D28-C28)/C28,"0%")) -> 130% | H28: TOTAL ECONOMIAS | I28: =SUM(I23:I27) -> 72855.71 | J28: =SUM(J23:J27) -> 60560.77 | K28: =SUM(K23:K27) -> -12294.94 | L28: -
A29: 60019-RESCISOES / IDENIZACOES | C29: =IFERROR(VLOOKUP(A29,PROJECAO_2026!$A$4:$F$120,6,FALSE),0) -> 1600 | D29: =IFERROR(VLOOKUP(A29,DIN_TAXA!$A$14:$G$121,7,FALSE),0) -> 2002.16 | E29: =D29-C29 -> 402.16 | F29: =IF(C29=0,IF(D29=0,"0%","N/A"),TEXT((D29-C29)/C29,"0%")) -> 25%
A30: 60014-FERIAS | C30: =IFERROR(VLOOKUP(A30,PROJECAO_2026!$A$4:$F$120,6,FALSE),0) -> 2000 | D30: =IFERROR(VLOOKUP(A30,DIN_TAXA!$A$14:$G$121,7,FALSE),0) -> 2245.5 | E30: =D30-C30 -> 245.5 | F30: =IF(C30=0,IF(D30=0,"0%","N/A"),TEXT((D30-C30)/C30,"0%")) -> 12% | H30: 📌 Os quadros acima são atualizados automaticamente quando os dados da DIN_TAXA são alterados
A31: 60068-CONTABILIDADE | C31: =IFERROR(VLOOKUP(A31,PROJECAO_2026!$A$4:$F$120,6,FALSE),0) -> 1646 | D31: =IFERROR(VLOOKUP(A31,DIN_TAXA!$A$14:$G$121,7,FALSE),0) -> 1621 | E31: =D31-C31 -> -25 | F31: =IF(C31=0,IF(D31=0,"0%","N/A"),TEXT((D31-C31)/C31,"0%")) -> -2%
A32: 60027-AJUDA DE CUSTOS PESSOAL | C32: =IFERROR(VLOOKUP(A32,PROJECAO_2026!$A$4:$F$120,6,FALSE),0) -> 1942.4733 | D32: =IFERROR(VLOOKUP(A32,DIN_TAXA!$A$14:$G$121,7,FALSE),0) -> 1980 | E32: =D32-C32 -> 37.526667 | F32: =IF(C32=0,IF(D32=0,"0%","N/A"),TEXT((D32-C32)/C32,"0%")) -> 2%
A33: 60043-AGUA E ESGOTO | C33: =IFERROR(VLOOKUP(A33,PROJECAO_2026!$A$4:$F$120,6,FALSE),0) -> 1911.2533 | D33: =IFERROR(VLOOKUP(A33,DIN_TAXA!$A$14:$G$121,7,FALSE),0) -> 2516.22 | E33: =D33-C33 -> 604.96667 | F33: =IF(C33=0,IF(D33=0,"0%","N/A"),TEXT((D33-C33)/C33,"0%")) -> 32%
A34: 60008-EQUIPAMENTOS LOCADOS PARA ENSINO | C34: =IFERROR(VLOOKUP(A34,PROJECAO_2026!$A$4:$F$120,6,FALSE),0) -> 1861.3667 | D34: =IFERROR(VLOOKUP(A34,DIN_TAXA!$A$14:$G$121,7,FALSE),0) -> 1439.58 | E34: =D34-C34 -> -421.78667 | F34: =IF(C34=0,IF(D34=0,"0%","N/A"),TEXT((D34-C34)/C34,"0%")) -> -23%
A35: 60069-JURIDICO | C35: =IFERROR(VLOOKUP(A35,PROJECAO_2026!$A$4:$F$120,6,FALSE),0) -> 1621 | D35: =IFERROR(VLOOKUP(A35,DIN_TAXA!$A$14:$G$121,7,FALSE),0) -> 3601.34 | E35: =D35-C35 -> 1980.34 | F35: =IF(C35=0,IF(D35=0,"0%","N/A"),TEXT((D35-C35)/C35,"0%")) -> 122%
A36: 60020-FGTS RESCISORIO | C36: =IFERROR(VLOOKUP(A36,PROJECAO_2026!$A$4:$F$120,6,FALSE),0) -> 1100 | D36: =IFERROR(VLOOKUP(A36,DIN_TAXA!$A$14:$G$121,7,FALSE),0) -> 165.15 | E36: =D36-C36 -> -934.85 | F36: =IF(C36=0,IF(D36=0,"0%","N/A"),TEXT((D36-C36)/C36,"0%")) -> -85%
A37: 60083-TRANSPORTES E FRETES | C37: =IFERROR(VLOOKUP(A37,PROJECAO_2026!$A$4:$F$120,6,FALSE),0) -> 1212.6133 | D37: =IFERROR(VLOOKUP(A37,DIN_TAXA!$A$14:$G$121,7,FALSE),0) -> 1338.72 | E37: =D37-C37 -> 126.10667 | F37: =IF(C37=0,IF(D37=0,"0%","N/A"),TEXT((D37-C37)/C37,"0%")) -> 10%
A38: 60057-MATERIAL DE LIMPEZA E CONSERVACAO | C38: =IFERROR(VLOOKUP(A38,PROJECAO_2026!$A$4:$F$120,6,FALSE),0) -> 1206.0333 | D38: =IFERROR(VLOOKUP(A38,DIN_TAXA!$A$14:$G$121,7,FALSE),0) -> 2094.25 | E38: =D38-C38 -> 888.21667 | F38: =IF(C38=0,IF(D38=0,"0%","N/A"),TEXT((D38-C38)/C38,"0%")) -> 74%
A39: 60039-BOLSA ESTAGIARIOS | C39: =IFERROR(VLOOKUP(A39,PROJECAO_2026!$A$4:$F$120,6,FALSE),0) -> 974.28667 | D39: =IFERROR(VLOOKUP(A39,DIN_TAXA!$A$14:$G$121,7,FALSE),0) -> 129.97 | E39: =D39-C39 -> -844.31667 | F39: =IF(C39=0,IF(D39=0,"0%","N/A"),TEXT((D39-C39)/C39,"0%")) -> -87%
A40: 60081-SERVICO TECNOLOGIA DA INFORMACAO | C40: =IFERROR(VLOOKUP(A40,PROJECAO_2026!$A$4:$F$120,6,FALSE),0) -> 900 | D40: =IFERROR(VLOOKUP(A40,DIN_TAXA!$A$14:$G$121,7,FALSE),0) -> 900 | E40: =D40-C40 -> 0 | F40: =IF(C40=0,IF(D40=0,"0%","N/A"),TEXT((D40-C40)/C40,"0%")) -> 0%
A41: 70018-REPASSE CAU | C41: =IFERROR(VLOOKUP(A41,PROJECAO_2026!$A$4:$F$120,6,FALSE),0) -> 807.12 | D41: =IFERROR(VLOOKUP(A41,DIN_TAXA!$A$14:$G$121,7,FALSE),0) -> 0 | E41: =D41-C41 -> -807.12 | F41: =IF(C41=0,IF(D41=0,"0%","N/A"),TEXT((D41-C41)/C41,"0%")) -> -100%
A42: 60048-MANUTENCAO REFRIGERACAO | C42: =IFERROR(VLOOKUP(A42,PROJECAO_2026!$A$4:$F$120,6,FALSE),0) -> 702.71667 | D42: =IFERROR(VLOOKUP(A42,DIN_TAXA!$A$14:$G$121,7,FALSE),0) -> 0 | E42: =D42-C42 -> -702.71667 | F42: =IF(C42=0,IF(D42=0,"0%","N/A"),TEXT((D42-C42)/C42,"0%")) -> -100%
... A73: 60076-CARTORIO | C73: =IFERROR(VLOOKUP(A73,PROJECAO_2026!$A$4:$F$120,6,FALSE),0) -> 11.693333 | D73: =IFERROR(VLOOKUP(A73,DIN_TAXA!$A$14:$G$121,7,FALSE),0) -> 0 | E73: =D73-C73 -> -11.693333 | F73: =IF(C73=0,IF(D73=0,"0%","N/A"),TEXT((D73-C73)/C73,"0%")) -> -100%
A74: 60015-13º SALARIO | C74: 0 | D74: =IFERROR(VLOOKUP(A74,DIN_TAXA!$A$14:$G$121,7,FALSE),0) -> 0 | E74: =D74-C74 -> 0 | F74: =IF(C74=0,IF(D74=0,"0%","N/A"),TEXT((D74-C74)/C74,"0%")) -> 0%
A75: 60021-PENSAO ALIMENTICIA | C75: 0 | D75: =IFERROR(VLOOKUP(A75,DIN_TAXA!$A$14:$G$121,7,FALSE),0) -> 0 | E75: =D75-C75 -> 0 | F75: =IF(C75=0,IF(D75=0,"0%","N/A"),TEXT((D75-C75)/C75,"0%")) -> 0%
A76: 60025-CESTAS BASICAS / CESTAS NATALINAS | C76: 0 | D76: =IFERROR(VLOOKUP(A76,DIN_TAXA!$A$14:$G$121,7,FALSE),0) -> 0 | E76: =D76-C76 -> 0 | F76: =IF(C76=0,IF(D76=0,"0%","N/A"),TEXT((D76-C76)/C76,"0%")) -> 0%
A77: 60028-COMISSOES | C77: 0 | D77: =IFERROR(VLOOKUP(A77,DIN_TAXA!$A$14:$G$121,7,FALSE),0) -> 0 | E77: =D77-C77 -> 0 | F77: =IF(C77=0,IF(D77=0,"0%","N/A"),TEXT((D77-C77)/C77,"0%")) -> 0%
A78: 60029-BONIFICACOES | C78: 0 | D78: =IFERROR(VLOOKUP(A78,DIN_TAXA!$A$14:$G$121,7,FALSE),0) -> 0 | E78: =D78-C78 -> 0 | F78: =IF(C78=0,IF(D78=0,"0%","N/A"),TEXT((D78-C78)/C78,"0%")) -> 0%
A79: 60036-EPI'S | C79: 0 | D79: =IFERROR(VLOOKUP(A79,DIN_TAXA!$A$14:$G$121,7,FALSE),0) -> 0 | E79: =D79-C79 -> 0 | F79: =IF(C79=0,IF(D79=0,"0%","N/A"),TEXT((D79-C79)/C79,"0%")) -> 0%
A80: 60037-FARDAMENTO COLABORADORES | C80: 0 | D80: =IFERROR(VLOOKUP(A80,DIN_TAXA!$A$14:$G$121,7,FALSE),0) -> 575.83 | E80: =D80-C80 -> 575.83 | F80: =IF(C80=0,IF(D80=0,"0%","N/A"),TEXT((D80-C80)/C80,"0%")) -> N/A
A81: 60051-SEGUROS PATRIMONIAIS | C81: 0 | D81: =IFERROR(VLOOKUP(A81,DIN_TAXA!$A$14:$G$121,7,FALSE),0) -> 0 | E81: =D81-C81 -> 0 | F81: =IF(C81=0,IF(D81=0,"0%","N/A"),TEXT((D81-C81)/C81,"0%")) -> 0%
A82: 60059-FERRAMENTAS E ACESSORIOS | C82: 0 | D82: =IFERROR(VLOOKUP(A82,DIN_TAXA!$A$14:$G$121,7,FALSE),0) -> 0 | E82: =D82-C82 -> 0 | F82: =IF(C82=0,IF(D82=0,"0%","N/A"),TEXT((D82-C82)/C82,"0%")) -> 0%
A83: 60060-LIVROS / REVISTAS / JORNAIS | C83: 0 | D83: =IFERROR(VLOOKUP(A83,DIN_TAXA!$A$14:$G$121,7,FALSE),0) -> 0 | E83: =D83-C83 -> 0 | F83: =IF(C83=0,IF(D83=0,"0%","N/A"),TEXT((D83-C83)/C83,"0%")) -> 0%
A84: 60064-FARMACIA E MEDICAMENTOS | C84: 0 | D84: =IFERROR(VLOOKUP(A84,DIN_TAXA!$A$14:$G$121,7,FALSE),0) -> 0 | E84: =D84-C84 -> 0 | F84: =IF(C84=0,IF(D84=0,"0%","N/A"),TEXT((D84-C84)/C84,"0%")) -> 0%
A85: 60071-SERVICO DE POSTAGEM E CORREIOS | C85: 0 | D85: =IFERROR(VLOOKUP(A85,DIN_TAXA!$A$14:$G$121,7,FALSE),0) -> 0 | E85: =D85-C85 -> 0 | F85: =IF(C85=0,IF(D85=0,"0%","N/A"),TEXT((D85-C85)/C85,"0%")) -> 0%
... A107: 60147-CREDENCIAMENTO NOVOS CURSOS | C107: 0 | D107: =IFERROR(VLOOKUP(A107,DIN_TAXA!$A$14:$G$121,7,FALSE),0) -> 3995.68 | E107: =D107-C107 -> 3995.68 | F107: =IF(C107=0,IF(D107=0,"0%","N/A"),TEXT((D107-C107)/C107,"0%")) -> N/A

Sheet PROJECAO_2026
A1: PROJEÇÃO DE DESPESAS 2026
A2: TOTAL MÊS | B2: =SUM(B4:B99) -> 311536.31 | C2: =SUM(C4:C99) -> 327176.73 | D2: =SUM(D4:D99) -> 332002.42 | E2: =SUM(E4:E99) -> 366849.77 | F2: =SUM(F4:F99) -> 325529.15 | G2: =SUM(G4:G99) -> 325529.15 | H2: =SUM(H4:H99) -> 325529.15 | I2: =SUM(I4:I99) -> 325529.15 | ... M2: =SUM(M4:M99) -> 325529.15 | N2: =SUM(B2:M2) -> 3941798.4
A3: Despesa | B3: Jan | C3: Fev | D3: Mar | E3: Abr | F3: Mai | G3: Jun | H3: Jul | I3: Ago | J3: Set | K3: Out | L3: Nov | M3: Dez | N3: Total Ano | O3: Base Projeção
A4: 60013-SALARIOS | B4: 34102 | C4: 34603 | D4: 31312.18 | E4: 32955.08 | F4: =IFERROR(AVERAGE($B$4:$E$4),0) -> 33243.065 | G4: =IFERROR(AVERAGE($B$4:$E$4),0) -> 33243.065 | H4: =IFERROR(AVERAGE($B$4:$E$4),0) -> 33243.065 | I4: =IFERROR(AVERAGE($B$4:$E$4),0) -> 33243.065 | J4: =IFERROR(AVERAGE($B$4:$E$4),0) -> 33243.065 | K4: =IFERROR(AVERAGE($B$4:$E$4),0) -> 33243.065 | L4: =IFERROR(AVERAGE($B$4:$E$4),0) -> 33243.065 | M4: =IFERROR(AVERAGE($B$4:$E$4),0) -> 33243.065 | N4: =SUM(B4:M4) -> 398916.78 | O4: Abril (ref.)
A5: 60004-INSTRUTOR | B5: 22440 | C5: 32472 | D5: 25036 | E5: 37714 | F5: 35000 | G5: =F5 -> 35000 | H5: =G5 -> 35000 | I5: =H5 -> 35000 | J5: =I5 -> 35000 | K5: =J5 -> 35000 | L5: =K5 -> 35000 | M5: =L5 -> 35000 | N5: =SUM(B5:M5) -> 397662 | O5: Maio (ref.)
A6: 60040-ALUGUEL | B6: 27343.18 | C6: 27343.18 | D6: 25123.8 | E6: 28087.8 | F6: =E6 -> 28087.8 | G6: =F6 -> 28087.8 | H6: =G6 -> 28087.8 | I6: =H6 -> 28087.8 | J6: =I6 -> 28087.8 | K6: =J6 -> 28087.8 | L6: =K6 -> 28087.8 | M6: =L6 -> 28087.8 | N6: =SUM(B6:M6) -> 332600.36 | O6: Abril (ref.)
A7: 60119-SIMPLES NACIONAL | B7: 20778.97 | C7: 18546.78 | D7: 19708.53 | E7: 18081.14 | F7: =IFERROR(AVERAGE(B7:D7),0) -> 19678.093 | G7: =IFERROR(AVERAGE(B7:D7),0) -> 19678.093 | H7: =IFERROR(AVERAGE(B7:D7),0) -> 19678.093 | I7: =IFERROR(AVERAGE(B7:D7),0) -> 19678.093 | J7: =IFERROR(AVERAGE(B7:D7),0) -> 19678.093 | K7: =IFERROR(AVERAGE(B7:D7),0) -> 19678.093 | L7: =IFERROR(AVERAGE(B7:D7),0) -> 19678.093 | M7: =IFERROR(AVERAGE(B7:D7),0) -> 19678.093 | N7: =SUM(B7:M7) -> 234540.17 | O7: Média Jan-Mar
A8: 60005-PRECEPTOR | B8: 12880 | C8: 9860 | D8: 13240 | E8: 16020 | F8: 16000 | G8: =F8 -> 16000 | H8: =G8 -> 16000 | I8: =H8 -> 16000 | J8: =I8 -> 16000 | K8: =J8 -> 16000 | L8: =K8 -> 16000 | M8: =L8 -> 16000 | N8: =SUM(B8:M8) -> 180000 | O8: Abril (ref.)
A9: 60052-ROYALTIES | B9: 12717.54 | C9: 24839.94 | D9: 20571.58 | E9: 26432.78 | F9: 22000 | G9: 22000 | H9: 22000 | I9: 22000 | J9: 22000 | K9: 22000 | L9: 22000 | M9: 22000 | N9: =SUM(B9:M9) -> 260561.84 | O9: Maio (ref.)
A10: 60106-JUROS E TAXAS SOBRE EMPRESTIMOS | B10: 19355.85 | C10: 21052.12 | D10: 21217.11 | E10: 21068.72 | F10: =IFERROR(AVERAGE(B10:D10),0) -> 20541.693 | G10: =IFERROR(AVERAGE(B10:D10),0) -> 20541.693 | H10: =IFERROR(AVERAGE(B10:D10),0) -> 20541.693 | I10: =IFERROR(AVERAGE(B10:D10),0) -> 20541.693 | J10: =IFERROR(AVERAGE(B10:D10),0) -> 20541.693 | K10: =IFERROR(AVERAGE(B10:D10),0) -> 20541.693 | L10: =IFERROR(AVERAGE(B10:D10),0) -> 20541.693 | M10: =IFERROR(AVERAGE(B10:D10),0) -> 20541.693 | N10: =SUM(B10:M10) -> 247027.35 | O10: Média Jan-Abr
A11: 60158-CARTAO DE CREDITO | B11: 11777.86 | C11: 13409.63 | D11: 12597.71 | E11: 10213.05 | F11: 10500 | G11: 10500 | H11: 10500 | I11: 10500 | J11: 10500 | K11: 10500 | L11: 10500 | M11: 10500 | N11: =SUM(B11:M11) -> 131998.25 | O11: Maio (ref.)
A12: 60030-PREMIACOES E GRATIFICACOES | B12: 10121 | C12: 21688 | D12: 17749 | E12: 17470 | F12: 12000 | G12: 12000 | H12: 12000 | I12: 12000 | J12: 12000 | K12: 12000 | L12: 12000 | M12: 12000 | N12: =SUM(B12:M12) -> 163028 | O12: Maio (ref.)
A13: 60001-APOSTILA | B13: 15185.37 | C13: 3152.57 | D13: 12695.6 | E13: 21146.35 | F13: =IFERROR(AVERAGE(B13:D13),0) -> 10344.513 | G13: =IFERROR(AVERAGE(B13:D13),0) -> 10344.513 | H13: =IFERROR(AVERAGE(B13:D13),0) -> 10344.513 | I13: =IFERROR(AVERAGE(B13:D13),0) -> 10344.513 | J13: =IFERROR(AVERAGE(B13:D13),0) -> 10344.513 | K13: =IFERROR(AVERAGE(B13:D13),0) -> 10344.513 | L13: =IFERROR(AVERAGE(B13:D13),0) -> 10344.513 | M13: =IFERROR(AVERAGE(B13:D13),0) -> 10344.513 | N13: =SUM(B13:M13) -> 134936 | O13: Média Jan-Mar
A14: 60109-MIDIA DE INTERNET | B14: 11910.26 | C14: 12041.64 | D14: 12000.93 | E14: 11732.48 | F14: =IFERROR(AVERAGE(B14:D14),0) -> 11984.277 | G14: =IFERROR(AVERAGE(B14:D14),0) -> 11984.277 | H14: =IFERROR(AVERAGE(B14:D14),0) -> 11984.277 | I14: =IFERROR(AVERAGE(B14:D14),0) -> 11984.277 | J14: =IFERROR(AVERAGE(B14:D14),0) -> 11984.277 | K14: =IFERROR(AVERAGE(B14:D14),0) -> 11984.277 | L14: =IFERROR(AVERAGE(B14:D14),0) -> 11984.277 | M14: =IFERROR(AVERAGE(B14:D14),0) -> 11984.277 | N14: =SUM(B14:M14) -> 143559.52 | O14: Média Jan-Abr
A15: 60053-FUNDO DE PROPAGANDA | B15: 11568.26 | C15: 11802.77 | D15: 12392.42 | E15: 9304.76 | F15: =IFERROR(AVERAGE(B15:D15),0) -> 11921.15 | G15: =IFERROR(AVERAGE(B15:D15),0) -> 11921.15 | H15: =IFERROR(AVERAGE(B15:D15),0) -> 11921.15 | I15: =IFERROR(AVERAGE(B15:D15),0) -> 11921.15 | J15: =IFERROR(AVERAGE(B15:D15),0) -> 11921.15 | K15: =IFERROR(AVERAGE(B15:D15),0) -> 11921.15 | L15: =IFERROR(AVERAGE(B15:D15),0) -> 11921.15 | M15: =IFERROR(AVERAGE(B15:D15),0) -> 11921.15 | N15: =SUM(B15:M15) -> 140437.41 | O15: Média Jan-Mar
A16: 60023-VALE TRANSPORTE | B16: 10509.42 | C16: 8159.72 | D16: 10185.02 | E16: 9242.4 | F16: =IFERROR(AVERAGE(B16:D16),0) -> 9618.0533 | G16: =IFERROR(AVERAGE(B16:D16),0) -> 9618.0533 | H16: =IFERROR(AVERAGE(B16:D16),0) -> 9618.0533 | I16: =IFERROR(AVERAGE(B16:D16),0) -> 9618.0533 | J16: =IFERROR(AVERAGE(B16:D16),0) -> 9618.0533 | K16: =IFERROR(AVERAGE(B16:D16),0) -> 9618.0533 | L16: =IFERROR(AVERAGE(B16:D16),0) -> 9618.0533 | M16: =IFERROR(AVERAGE(B16:D16),0) -> 9618.0533 | N16: =SUM(B16:M16) -> 115040.99 | O16: Média Jan-Abr
A17: 60009-SERVICOS DE ASSESSORIA PEDAGOGICA | B17: 8260 | C17: 7500 | D17: 8468 | E17: 9037 | F17: =IFERROR(AVERAGE(B17:D17),0) -> 8076 | G17: =IFERROR(AVERAGE(B17:D17),0) -> 8076 | H17: =IFERROR(AVERAGE(B17:D17),0) -> 8076 | I17: =IFERROR(AVERAGE(B17:D17),0) -> 8076 | J17: =IFERROR(AVERAGE(B17:D17),0) -> 8076 | K17: =IFERROR(AVERAGE(B17:D17),0) -> 8076 | L17: =IFERROR(AVERAGE(B17:D17),0) -> 8076 | M17: =IFERROR(AVERAGE(B17:D17),0) -> 8076 | N17: =SUM(B17:M17) -> 97873 | O17: Média Jan-Mar
A18: 60012-PRO LABORE | B18: 12000 | C18: 12000 | D18: 12000 | E18: 12000 | F18: =IFERROR(AVERAGE(B18:D18),0) -> 12000 | G18: =IFERROR(AVERAGE(B18:D18),0) -> 12000 | H18: =IFERROR(AVERAGE(B18:D18),0) -> 12000 | I18: =IFERROR(AVERAGE(B18:D18),0) -> 12000 | J18: =IFERROR(AVERAGE(B18:D18),0) -> 12000 | K18: =IFERROR(AVERAGE(B18:D18),0) -> 12000 | L18: =IFERROR(AVERAGE(B18:D18),0) -> 12000 | M18: =IFERROR(AVERAGE(B18:D18),0) -> 12000 | N18: =SUM(B18:M18) -> 144000 | O18: Valor Fixo
A19: 60022-VALE ALIMENTACAO / REFEICAO | B19: 5462.47 | C19: 5619.24 | D19: 4852.98 | E19: 5652.19 | F19: =IFERROR(AVERAGE(B19:D19),0) -> 5311.5633 | G19: =IFERROR(AVERAGE(B19:D19),0) -> 5311.5633 | H19: =IFERROR(AVERAGE(B19:D19),0) -> 5311.5633 | I19: =IFERROR(AVERAGE(B19:D19),0) -> 5311.5633 | J19: =IFERROR(AVERAGE(B19:D19),0) -> 5311.5633 | K19: =IFERROR(AVERAGE(B19:D19),0) -> 5311.5633 | L19: =IFERROR(AVERAGE(B19:D19),0) -> 5311.5633 | M19: =IFERROR(AVERAGE(B19:D19),0) -> 5311.5633 | N19: =SUM(B19:M19) -> 64079.387 | O19: Média Jan-Mar
A20: 60080-ALUGUEL / ASSINATURA DE SISTEMAS | B20: 3571.66 | C20: 4197.53 | D20: 4407.36 | E20: 3650.66 | F20: =IFERROR(AVERAGE(B20:D20),0) -> 4058.85 | G20: =IFERROR(AVERAGE(B20:D20),0) -> 4058.85 | H20: =IFERROR(AVERAGE(B20:D20),0) -> 4058.85 | I20: =IFERROR(AVERAGE(B20:D20),0) -> 4058.85 | J20: =IFERROR(AVERAGE(B20:D20),0) -> 4058.85 | K20: =IFERROR(AVERAGE(B20:D20),0) -> 4058.85 | L20: =IFERROR(AVERAGE(B20:D20),0) -> 4058.85 | M20: =IFERROR(AVERAGE(B20:D20),0) -> 4058.85 | N20: =SUM(B20:M20) -> 48298.01 | O20: Média Jan-Mar
A21: 60159-CONTRA PARTIDA DE ESTAGIO | B21: 3227.5 | C21: 3527.5 | D21: 9830.59 | E21: 10279.2 | F21: 3500 | G21: 3500 | H21: 3500 | I21: 3500 | J21: 3500 | K21: 3500 | L21: 3500 | M21: 3500 | N21: =SUM(B21:M21) -> 54864.79 | O21: Maio (ref.)
A22: 60067-OUTRAS DESPESAS | B22: 1413.36 | C22: 405.87 | D22: 0 | E22: 524.29 | F22: =IFERROR(AVERAGE(B22:D22),0) -> 606.41 | G22: =IFERROR(AVERAGE(B22:D22),0) -> 606.41 | H22: =IFERROR(AVERAGE(B22:D22),0) -> 606.41 | I22: =IFERROR(AVERAGE(B22:D22),0) -> 606.41 | J22: =IFERROR(AVERAGE(B22:D22),0) -> 606.41 | K22: =IFERROR(AVERAGE(B22:D22),0) -> 606.41 | L22: =IFERROR(AVERAGE(B22:D22),0) -> 606.41 | M22: =IFERROR(AVERAGE(B22:D22),0) -> 606.41 | N22: =SUM(B22:M22) -> 7194.8 | O22: Média Jan-Mar
A23: 60018-FGTS SALARIO | B23: 5776.39 | C23: 4717.62 | D23: 4586.75 | E23: 4640.87 | F23: =IFERROR(AVERAGE(B23:D23),0) -> 5026.92 | G23: =IFERROR(AVERAGE(B23:D23),0) -> 5026.92 | H23: =IFERROR(AVERAGE(B23:D23),0) -> 5026.92 | I23: =IFERROR(AVERAGE(B23:D23),0) -> 5026.92 | J23: =IFERROR(AVERAGE(B23:D23),0) -> 5026.92 | K23: =IFERROR(AVERAGE(B23:D23),0) -> 5026.92 | L23: =IFERROR(AVERAGE(B23:D23),0) -> 5026.92 | M23: =IFERROR(AVERAGE(B23:D23),0) -> 5026.92 | N23: =SUM(B23:M23) -> 59936.99 | O23: Média Jan-Mar
A24: 60069-JURIDICO | B24: 1621 | C24: 9827.92 | D24: 2154.49 | E24: 12509.06 | F24: 1621 | G24: 1621 | H24: 1621 | I24: 1621 | J24: 1621 | K24: 1621 | L24: 1621 | M24: 1621 | N24: =SUM(B24:M24) -> 39080.47 | O24: Média Jan-Mar
A25: 60003-FARDAMENTO ALUNOS | B25: 1996.8 | C25: 1567 | D25: 4003.78 | E25: 4646.21 | F25: =IFERROR(AVERAGE(B25:D25),0) -> 2522.5267 | G25: =IFERROR(AVERAGE(B25:D25),0) -> 2522.5267 | H25: =IFERROR(AVERAGE(B25:D25),0) -> 2522.5267 | I25: =IFERROR(AVERAGE(B25:D25),0) -> 2522.5267 | J25: =IFERROR(AVERAGE(B25:D25),0) -> 2522.5267 | K25: =IFERROR(AVERAGE(B25:D25),0) -> 2522.5267 | L25: =IFERROR(AVERAGE(B25:D25),0) -> 2522.5267 | M25: =IFERROR(AVERAGE(B25:D25),0) -> 2522.5267 | N25: =SUM(B25:M25) -> 32394.003 | O25: Média Jan-Mar
A26: 60047-MANUTENCAO PREDIAL | B26: 6327 | C26: 4782.58 | D26: 3910.29 | E26: 3708.68 | F26: =IFERROR(AVERAGE(D26:E26),0) -> 3809.485 | G26: =F26 -> 3809.485 | H26: =G26 -> 3809.485 | I26: =H26 -> 3809.485 | J26: =I26 -> 3809.485 | K26: =J26 -> 3809.485 | L26: =K26 -> 3809.485 | M26: =L26 -> 3809.485 | N26: =SUM(B26:M26) -> 49204.43 | O26: Média Jan-Mar
A27: 60019-RESCISOES / IDENIZACOES | B27: 1016.14 | C27: 11.26 | D27: 6281.17 | E27: 1600.17 | F27: 1600 | G27: 1600 | H27: 1600 | I27: 1600 | J27: 1600 | K27: 1600 | L27: 1600 | M27: 1600 | N27: =SUM(B27:M27) -> 21708.74 | O27: Abril (ref.)
A28: 60017-INSS SALARIO | B28: 2587.6 | C28: 2614.42 | D28: 2531.11 | E28: 2783.83 | F28: =IFERROR(AVERAGE(B28:D28),0) -> 2577.71 | G28: =IFERROR(AVERAGE(B28:D28),0) -> 2577.71 | H28: =IFERROR(AVERAGE(B28:D28),0) -> 2577.71 | I28: =IFERROR(AVERAGE(B28:D28),0) -> 2577.71 | J28: =IFERROR(AVERAGE(B28:D28),0) -> 2577.71 | K28: =IFERROR(AVERAGE(B28:D28),0) -> 2577.71 | L28: =IFERROR(AVERAGE(B28:D28),0) -> 2577.71 | M28: =IFERROR(AVERAGE(B28:D28),0) -> 2577.71 | N28: =SUM(B28:M28) -> 31138.64 | O28: Média Jan-Mar
A29: 60098-TARIFAS BANCARIAS | B29: 4883.76 | C29: 3885.9 | D29: 4547.63 | E29: 4658.27 | F29: =IFERROR(AVERAGE(B29:D29),0) -> 4439.0967 | G29: =IFERROR(AVERAGE(B29:D29),0) -> 4439.0967 | H29: =IFERROR(AVERAGE(B29:D29),0) -> 4439.0967 | I29: =IFERROR(AVERAGE(B29:D29),0) -> 4439.0967 | J29: =IFERROR(AVERAGE(B29:D29),0) -> 4439.0967 | K29: =IFERROR(AVERAGE(B29:D29),0) -> 4439.0967 | L29: =IFERROR(AVERAGE(B29:D29),0) -> 4439.0967 | M29: =IFERROR(AVERAGE(B29:D29),0) -> 4439.0967 | N29: =SUM(B29:M29) -> 53488.333 | O29: Média Jan-Mar
A30: 60042-ENERGIA ELETRICA | B30: 4397.03 | C30: 4645.44 | D30: 4693.61 | E30: 4100.17 | F30: =IFERROR(AVERAGE(B30:D30),0) -> 4578.6933 | G30: =IFERROR(AVERAGE(B30:D30),0) -> 4578.6933 | H30: =IFERROR(AVERAGE(B30:D30),0) -> 4578.6933 | I30: =IFERROR(AVERAGE(B30:D30),0) -> 4578.6933 | J30: =IFERROR(AVERAGE(B30:D30),0) -> 4578.6933 | K30: =IFERROR(AVERAGE(B30:D30),0) -> 4578.6933 | L30: =IFERROR(AVERAGE(B30:D30),0) -> 4578.6933 | M30: =IFERROR(AVERAGE(B30:D30),0) -> 4578.6933 | N30: =SUM(B30:M30) -> 54465.797 | O30: Média Jan-Mar
A31: 60043-AGUA E ESGOTO | B31: 2250.53 | C31: 1027.31 | D31: 2455.92 | E31: 1757.08 | F31: =IFERROR(AVERAGE(B31:D31),0) -> 1911.2533 | G31: =IFERROR(AVERAGE(B31:D31),0) -> 1911.2533 | H31: =IFERROR(AVERAGE(B31:D31),0) -> 1911.2533 | I31: =IFERROR(AVERAGE(B31:D31),0) -> 1911.2533 | J31: =IFERROR(AVERAGE(B31:D31),0) -> 1911.2533 | K31: =IFERROR(AVERAGE(B31:D31),0) -> 1911.2533 | L31: =IFERROR(AVERAGE(B31:D31),0) -> 1911.2533 | M31: =IFERROR(AVERAGE(B31:D31),0) -> 1911.2533 | N31: =SUM(B31:M31) -> 22780.867 | O31: Média Jan-Mar
A32: 60015-13º SALARIO | B32: 0 | C32: 0 | D32: 0 | E32: 0 | F32: =IFERROR(AVERAGE(B32:D32),0) -> 0 | G32: =IFERROR(AVERAGE(B32:D32),0) -> 0 | H32: =IFERROR(AVERAGE(B32:D32),0) -> 0 | I32: =IFERROR(AVERAGE(B32:D32),0) -> 0 | J32: =IFERROR(AVERAGE(B32:D32),0) -> 0 | K32: =IFERROR(AVERAGE(B32:D32),0) -> 0 | L32: =IFERROR(AVERAGE(B32:D32),0) -> 0 | M32: =IFERROR(AVERAGE(B32:D32),0) -> 0 | N32: =SUM(B32:M32) -> 0 | O32: Sem movimento
A33: 60014-FERIAS | B33: 2243.96 | C33: 1000 | D33: 3318 | E33: 1726.91 | F33: 2000 | G33: 2000 | H33: 2000 | I33: 2000 | J33: 2000 | K33: 2000 | L33: 2000 | M33: 2000 | N33: =SUM(B33:M33) -> 24288.87 | O33: Maio (ref.)
A34: 60068-CONTABILIDADE | B34: 3060.22 | C34: 1621 | D34: 1628.5 | E34: 1646 | F34: 1646 | G34: 1646 | H34: 1646 | I34: 1646 | J34: 1646 | K34: 1646 | L34: 1646 | M34: 1646 | N34: =SUM(B34:M34) -> 21123.72 | O34: Abril (ref.)
A35: 60027-AJUDA DE CUSTOS PESSOAL | B35: 1500 | C35: 2535.42 | D35: 1792 | E35: 1859.64 | F35: =IFERROR(AVERAGE(B35:D35),0) -> 1942.4733 | G35: =IFERROR(AVERAGE(B35:D35),0) -> 1942.4733 | H35: =IFERROR(AVERAGE(B35:D35),0) -> 1942.4733 | I35: =IFERROR(AVERAGE(B35:D35),0) -> 1942.4733 | J35: =IFERROR(AVERAGE(B35:D35),0) -> 1942.4733 | K35: =IFERROR(AVERAGE(B35:D35),0) -> 1942.4733 | L35: =IFERROR(AVERAGE(B35:D35),0) -> 1942.4733 | M35: =IFERROR(AVERAGE(B35:D35),0) -> 1942.4733 | N35: =SUM(B35:M35) -> 23226.847 | O35: Média Jan-Mar
A36: 60057-MATERIAL DE LIMPEZA E CONSERVACAO | B36: 1721.21 | C36: 1708.28 | D36: 188.61 | E36: 1818.99 | F36: =IFERROR(AVERAGE(B36:D36),0) -> 1206.0333 | G36: =IFERROR(AVERAGE(B36:D36),0) -> 1206.0333 | H36: =IFERROR(AVERAGE(B36:D36),0) -> 1206.0333 | I36: =IFERROR(AVERAGE(B36:D36),0) -> 1206.0333 | J36: =IFERROR(AVERAGE(B36:D36),0) -> 1206.0333 | K36: =IFERROR(AVERAGE(B36:D36),0) -> 1206.0333 | L36: =IFERROR(AVERAGE(B36:D36),0) -> 1206.0333 | M36: =IFERROR(AVERAGE(B36:D36),0) -> 1206.0333 | N36: =SUM(B36:M36) -> 15085.357 | O36: Média Jan-Mar
A37: 60020-FGTS RESCISORIO | B37: 2707.76 | C37: 0 | D37: 1125.59 | E37: 864.88 | F37: 1100 | G37: 1100 | H37: 1100 | I37: 1100 | J37: 1100 | K37: 1100 | L37: 1100 | M37: 1100 | N37: =SUM(B37:M37) -> 13498.23 | O37: Maio (ref.)
A38: 60078-LOCACAO DE EQUIPAMENTOS | B38: 390 | C38: 431.59 | D38: 390 | E38: 233.3 | F38: =IFERROR(AVERAGE(B38:D38),0) -> 403.86333 | G38: =IFERROR(AVERAGE(B38:D38),0) -> 403.86333 | H38: =IFERROR(AVERAGE(B38:D38),0) -> 403.86333 | I38: =IFERROR(AVERAGE(B38:D38),0) -> 403.86333 | J38: =IFERROR(AVERAGE(B38:D38),0) -> 403.86333 | K38: =IFERROR(AVERAGE(B38:D38),0) -> 403.86333 | L38: =IFERROR(AVERAGE(B38:D38),0) -> 403.86333 | M38: =IFERROR(AVERAGE(B38:D38),0) -> 403.86333 | N38: =SUM(B38:M38) -> 4675.7967 | O38: Média Jan-Mar
A39: 60083-TRANSPORTES E FRETES | B39: 957.55 | C39: 1679.83 | D39: 1000.46 | E39: 1480.37 | F39: =IFERROR(AVERAGE(B39:D39),0) -> 1212.6133 | G39: =IFERROR(AVERAGE(B39:D39),0) -> 1212.6133 | H39: =IFERROR(AVERAGE(B39:D39),0) -> 1212.6133 | I39: =IFERROR(AVERAGE(B39:D39),0) -> 1212.6133 | J39: =IFERROR(AVERAGE(B39:D39),0) -> 1212.6133 | K39: =IFERROR(AVERAGE(B39:D39),0) -> 1212.6133 | L39: =IFERROR(AVERAGE(B39:D39),0) -> 1212.6133 | M39: =IFERROR(AVERAGE(B39:D39),0) -> 1212.6133 | N39: =SUM(B39:M39) -> 14819.117 | O39: Média Jan-Mar
A40: 60081-SERVICO TECNOLOGIA DA INFORMACAO | B40: 900 | C40: 900 | D40: 900 | E40: 900 | F40: =IFERROR(AVERAGE(B40:D40),0) -> 900 | G40: =IFERROR(AVERAGE(B40:D40),0) -> 900 | H40: =IFERROR(AVERAGE(B40:D40),0) -> 900 | I40: =IFERROR(AVERAGE(B40:D40),0) -> 900 | J40: =IFERROR(AVERAGE(B40:D40),0) -> 900 | K40: =IFERROR(AVERAGE(B40:D40),0) -> 900 | L40: =IFERROR(AVERAGE(B40:D40),0) -> 900 | M40: =IFERROR(AVERAGE(B40:D40),0) -> 900 | N40: =SUM(B40:M40) -> 10800 | O40: Valor Fixo
A41: 60049-MANUTENCAO DE EQUIPAMENTOS | B41: 0 | C41: 180 | D41: 99 | E41: 500 | F41: =IFERROR(AVERAGE(B41:D41),0) -> 93 | G41: =IFERROR(AVERAGE(B41:D41),0) -> 93 | H41: =IFERROR(AVERAGE(B41:D41),0) -> 93 | I41: =IFERROR(AVERAGE(B41:D41),0) -> 93 | J41: =IFERROR(AVERAGE(B41:D41),0) -> 93 | K41: =IFERROR(AVERAGE(B41:D41),0) -> 93 | L41: =IFERROR(AVERAGE(B41:D41),0) -> 93 | M41: =IFERROR(AVERAGE(B41:D41),0) -> 93 | N41: =SUM(B41:M41) -> 1523 | O41: Média Jan-Mar
A42: 60084-OUTRAS CONSULTORIAS | B42: 2333 | C42: 3331 | D42: 3841.22 | E42: 3044.73 | F42: =IFERROR(AVERAGE(B42:D42),0) -> 3168.4067 | G42: =IFERROR(AVERAGE(B42:D42),0) -> 3168.4067 | H42: =IFERROR(AVERAGE(B42:D42),0) -> 3168.4067 | I42: =IFERROR(AVERAGE(B42:D42),0) -> 3168.4067 | J42: =IFERROR(AVERAGE(B42:D42),0) -> 3168.4067 | K42: =IFERROR(AVERAGE(B42:D42),0) -> 3168.4067 | L42: =IFERROR(AVERAGE(B42:D42),0) -> 3168.4067 | M42: =IFERROR(AVERAGE(B42:D42),0) -> 3168.4067 | N42: =SUM(B42:M42) -> 37897.203 | O42: Média Jan-Abr
A43: 60010-DEVOLUCAO DE PARCELAS | B43: 0 | C43: 297.5 | D43: 39.84 | E43: 75 | F43: =IFERROR(AVERAGE(B43:D43),0) -> 112.44667 | G43: =IFERROR(AVERAGE(B43:D43),0) -> 112.44667 | H43: =IFERROR(AVERAGE(B43:D43),0) -> 112.44667 | I43: =IFERROR(AVERAGE(B43:D43),0) -> 112.44667 | J43: =IFERROR(AVERAGE(B43:D43),0) -> 112.44667 | K43: =IFERROR(AVERAGE(B43:D43),0) -> 112.44667 | L43: =IFERROR(AVERAGE(B43:D43),0) -> 112.44667 | M43: =IFERROR(AVERAGE(B43:D43),0) -> 112.44667 | N43: =SUM(B43:M43) -> 1311.9133 | O43: Média Jan-Mar
A44: 60039-BOLSA ESTAGIARIOS | B44: 883.85 | C44: 879.97 | D44: 1159.04 | E44: 1884.97 | F44: =IFERROR(AVERAGE(B44:D44),0) -> 974.28667 | G44: =IFERROR(AVERAGE(B44:D44),0) -> 974.28667 | H44: =IFERROR(AVERAGE(B44:D44),0) -> 974.28667 | I44: =IFERROR(AVERAGE(B44:D44),0) -> 974.28667 | J44: =IFERROR(AVERAGE(B44:D44),0) -> 974.28667 | K44: =IFERROR(AVERAGE(B44:D44),0) -> 974.28667 | L44: =IFERROR(AVERAGE(B44:D44),0) -> 974.28667 | M44: =IFERROR(AVERAGE(B44:D44),0) -> 974.28667 | N44: =SUM(B44:M44) -> 12602.123 | O44: Média Jan-Mar
A45: 60058-MATERIAL DE USO E CONSUMO | B45: 485.02 | C45: 108.49 | D45: 1322.35 | E45: 826.86 | F45: =IFERROR(AVERAGE(B45:D45),0) -> 638.62 | G45: =IFERROR(AVERAGE(B45:D45),0) -> 638.62 | H45: =IFERROR(AVERAGE(B45:D45),0) -> 638.62 | I45: =IFERROR(AVERAGE(B45:D45),0) -> 638.62 | J45: =IFERROR(AVERAGE(B45:D45),0) -> 638.62 | K45: =IFERROR(AVERAGE(B45:D45),0) -> 638.62 | L45: =IFERROR(AVERAGE(B45:D45),0) -> 638.62 | M45: =IFERROR(AVERAGE(B45:D45),0) -> 638.62 | N45: =SUM(B45:M45) -> 7851.68 | O45: Média Jan-Mar
A46: 60045-INTERNET E CONEXOES | B46: 605 | C46: 605 | D46: 605 | E46: 605 | F46: =IFERROR(AVERAGE(B46:D46),0) -> 605 | G46: =IFERROR(AVERAGE(B46:D46),0) -> 605 | H46: =IFERROR(AVERAGE(B46:D46),0) -> 605 | I46: =IFERROR(AVERAGE(B46:D46),0) -> 605 | J46: =IFERROR(AVERAGE(B46:D46),0) -> 605 | K46: =IFERROR(AVERAGE(B46:D46),0) -> 605 | L46: =IFERROR(AVERAGE(B46:D46),0) -> 605 | M46: =IFERROR(AVERAGE(B46:D46),0) -> 605 | N46: =SUM(B46:M46) -> 7260 | O46: Valor Fixo
A47: 60048-MANUTENCAO REFRIGERACAO | B47: 1750 | C47: 358.15 | D47: 0 | E47: 1900 | F47: =IFERROR(AVERAGE(B47:D47),0) -> 702.71667 | G47: =IFERROR(AVERAGE(B47:D47),0) -> 702.71667 | H47: =IFERROR(AVERAGE(B47:D47),0) -> 702.71667 | I47: =IFERROR(AVERAGE(B47:D47),0) -> 702.71667 | J47: =IFERROR(AVERAGE(B47:D47),0) -> 702.71667 | K47: =IFERROR(AVERAGE(B47:D47),0) -> 702.71667 | L47: =IFERROR(AVERAGE(B47:D47),0) -> 702.71667 | M47: =IFERROR(AVERAGE(B47:D47),0) -> 702.71667 | N47: =SUM(B47:M47) -> 9629.8833 | O47: Média Jan-Mar
A48: 60100-TARIFA PIX | B48: 0 | C48: 0 | D48: 0 | E48: 0 | F48: =IFERROR(AVERAGE(B48:D48),0) -> 0 | G48: =IFERROR(AVERAGE(B48:D48),0) -> 0 | H48: =IFERROR(AVERAGE(B48:D48),0) -> 0 | I48: =IFERROR(AVERAGE(B48:D48),0) -> 0 | J48: =IFERROR(AVERAGE(B48:D48),0) -> 0 | K48: =IFERROR(AVERAGE(B48:D48),0) -> 0 | L48: =IFERROR(AVERAGE(B48:D48),0) -> 0 | M48: =IFERROR(AVERAGE(B48:D48),0) -> 0 | N48: =SUM(B48:M48) -> 0 | O48: Sem movimento
A49: 60077-IMPRESSOES / COPIAS / CARIMBOS / CARTOES | B49: 60 | C49: 0 | D49: 6 | E49: 0 | F49: =IFERROR(AVERAGE(B49:D49),0) -> 22 | G49: =IFERROR(AVERAGE(B49:D49),0) -> 22 | H49: =IFERROR(AVERAGE(B49:D49),0) -> 22 | I49: =IFERROR(AVERAGE(B49:D49),0) -> 22 | J49: =IFERROR(AVERAGE(B49:D49),0) -> 22 | K49: =IFERROR(AVERAGE(B49:D49),0) -> 22 | L49: =IFERROR(AVERAGE(B49:D49),0) -> 22 | M49: =IFERROR(AVERAGE(B49:D49),0) -> 22 | N49: =SUM(B49:M49) -> 242 | O49: Média Jan-Mar
... A99: 60028-COMISSOES | B99: 0 | C99: 0 | D99: 0 | E99: 50 | F99: =IFERROR(AVERAGE(B99:D99),0) -> 0 | G99: =IFERROR(AVERAGE(B99:D99),0) -> 0 | H99: =IFERROR(AVERAGE(B99:D99),0) -> 0 | I99: =IFERROR(AVERAGE(B99:D99),0) -> 0 | J99: =IFERROR(AVERAGE(B99:D99),0) -> 0 | K99: =IFERROR(AVERAGE(B99:D99),0) -> 0 | L99: =IFERROR(AVERAGE(B99:D99),0) -> 0 | M99: =IFERROR(AVERAGE(B99:D99),0) -> 0 | N99: =SUM(B99:M99) -> 50 | O99: Sem movimento
A101: TOTAL GERAL | B101: =SUM(B4:B99) -> 311536.31 | C101: =SUM(C4:C99) -> 327176.73 | D101: =SUM(D4:D99) -> 332002.42 | E101: =SUM(E4:E99) -> 366849.77 | F101: =SUM(F4:F99) -> 325529.15 | G101: =SUM(G4:G99) -> 325529.15 | H101: =SUM(H4:H99) -> 325529.15 | I101: =SUM(I4:I99) -> 325529.15 | ... N101: =SUM(N4:N99) -> 3941798.4
A104: 📊 RESUMO DA PROJEÇÃO
A106: Descrição | B106: Valor
A107: Total Realizado (Jan-Abr) | B107: =SUM(B101:E101) -> 1337565.2
A108: Total Projetado (Mai-Dez) | B108: =SUM(F101:M101) -> 2604233.2
A109: Total Anual 2026 | B109: =N101 -> 3941798.4
A110: Média Mensal Projetada | B110: =N101/12 -> 328483.2
A112: 📌 METODOLOGIA:
A113: • INSTRUTOR e PRECEPTOR: projeção baseada em ABRIL (nível normal após recesso)
A114: 📅 VISÃO TRIMESTRAL
A116: Período | B116: Valor | C116: % do Ano | D116: Status
A117: Q1 (Jan-Mar) | B117: =SUM(B101:D101) -> 970715.46 | C117: =B117/N101 -> 0.24626208 | D117: Realizado
A118: Q2 (Abr-Jun) | B118: =SUM(E101:G101) -> 1017908.1 | C118: =B118/N101 -> 0.25823443 | D118: Parcial + Projeção
A119: Q3 (Jul-Set) | B119: =SUM(H101:J101) -> 976587.44 | C119: =B119/N101 -> 0.24775175 | D119: Projetado
A120: Q4 (Out-Dez) | B120: =SUM(K101:M101) -> 976587.44 | C120: =B120/N101 -> 0.24775175 | D120: Projetado
A121: TOTAL 2026 | B121: =SUM(B117:B120) -> 3941798.4 | C121: =SUM(C117:C120) -> 1

Sheet Gastos com a Franqueadora
A1: GASTOS COM A FRANQUEADORA - EVOLUÇÃO 2026
A4: Despesa | B4: Jan | C4: Fev | D4: Mar | E4: Abr | F4: Mai | G4: TOTAL 2026
A5: 60052-ROYALTIES | B5: =SUMIFS(BASE!$K:$K,BASE!$C:$C,$A5,BASE!$M:$M,2026,BASE!$D:$D,"01/2026") -> 2623.02 | C5: =SUMIFS(BASE!$K:$K,BASE!$C:$C,$A5,BASE!$M:$M,2026,BASE!$D:$D,"02/2026") -> 24839.94 | D5: =SUMIFS(BASE!$K:$K,BASE!$C:$C,$A5,BASE!$M:$M,2026,BASE!$D:$D,"03/2026") -> 20571.58 | E5: =SUMIFS(BASE!$K:$K,BASE!$C:$C,$A5,BASE!$M:$M,2026,BASE!$D:$D,"04/2026") -> 26432.78 | F5: =SUMIFS(BASE!$K:$K,BASE!$C:$C,$A5,BASE!$M:$M,2026,BASE!$D:$D,"05/2026") -> 24737.21 | G5: =SUM(B5:F5) -> 99204.53
A6: 60001-APOSTILA | B6: =SUMIFS(BASE!$K:$K,BASE!$C:$C,$A6,BASE!$M:$M,2026,BASE!$D:$D,"01/2026") -> 0 | C6: =SUMIFS(BASE!$K:$K,BASE!$C:$C,$A6,BASE!$M:$M,2026,BASE!$D:$D,"02/2026") -> 3152.57 | D6: =SUMIFS(BASE!$K:$K,BASE!$C:$C,$A6,BASE!$M:$M,2026,BASE!$D:$D,"03/2026") -> 1993.52 | E6: =SUMIFS(BASE!$K:$K,BASE!$C:$C,$A6,BASE!$M:$M,2026,BASE!$D:$D,"04/2026") -> 15622.75 | F6: =SUMIFS(BASE!$K:$K,BASE!$C:$C,$A6,BASE!$M:$M,2026,BASE!$D:$D,"05/2026") -> 3992.8 | G6: =SUM(B6:F6) -> 24761.64
A7: 60053-FUNDO DE PROPAGANDA | B7: =SUMIFS(BASE!$K:$K,BASE!$C:$C,$A7,BASE!$M:$M,2026,BASE!$D:$D,"01/2026") -> 11568.26 | C7: =SUMIFS(BASE!$K:$K,BASE!$C:$C,$A7,BASE!$M:$M,2026,BASE!$D:$D,"02/2026") -> 11802.77 | D7: =SUMIFS(BASE!$K:$K,BASE!$C:$C,$A7,BASE!$M:$M,2026,BASE!$D:$D,"03/2026") -> 12392.42 | E7: =SUMIFS(BASE!$K:$K,BASE!$C:$C,$A7,BASE!$M:$M,2026,BASE!$D:$D,"04/2026") -> 9304.76 | F7: =SUMIFS(BASE!$K:$K,BASE!$C:$C,$A7,BASE!$M:$M,2026,BASE!$D:$D,"05/2026") -> 13742.91 | G7: =SUM(B7:F7) -> 58811.12
A8: TOTAL FRANQUEADORA | B8: =SUM(B5:B7) -> 14191.28 | C8: =SUM(C5:C7) -> 39795.28 | D8: =SUM(D5:D7) -> 34957.52 | E8: =SUM(E5:E7) -> 51360.29 | F8: =SUM(F5:F7) -> 42472.92 | G8: =SUM(G5:G7) -> 182777.29
A10: TOTAL GERAL DESPESAS | B10: =DIN_TAXA!C121 -> 311536.31 | C10: =DIN_TAXA!D121 -> 327176.73 | D10: =DIN_TAXA!E121 -> 332050.92 | E10: =DIN_TAXA!F121 -> 366849.77 | F10: =DIN_TAXA!G121 -> 333682.87 | G10: =DIN_TAXA!H121 -> 1671296.6
A12: % REPRESENTATIVIDADE | B12: =IF(B10=0,0,B8/B10) -> 0.045552571 | C12: =IF(C10=0,0,C8/C10) -> 0.12163237 | D12: =IF(D10=0,0,D8/D10) -> 0.10527759 | E12: =IF(E10=0,0,E8/E10) -> 0.1400036 | F12: =IF(F10=0,0,F8/F10) -> 0.12728529 | G12: =IF(G10=0,0,G8/G10) -> 0.10936257
A14: % REPRESENTATIVIDADE POR DESPESA
A15: 60052-ROYALTIES | B15: =IF(B$10=0,0,B5/B$10) -> 0.0084196285 | C15: =IF(C$10=0,0,C5/C$10) -> 0.075922087 | D15: =IF(D$10=0,0,D5/D$10) -> 0.061953088 | E15: =IF(E$10=0,0,E5/E$10) -> 0.072053418 | F15: =IF(F$10=0,0,F5/F$10) -> 0.074133892 | G15: =IF(G$10=0,0,G5/G$10) -> 0.059357824
A16: 60001-APOSTILA | B16: =IF(B$10=0,0,B6/B$10) -> 0 | C16: =IF(C$10=0,0,C6/C$10) -> 0.0096356792 | D16: =IF(D$10=0,0,D6/D$10) -> 0.0060036575 | E16: =IF(E$10=0,0,E6/E$10) -> 0.042586234 | F16: =IF(F$10=0,0,F6/F$10) -> 0.011965852 | G16: =IF(G$10=0,0,G6/G$10) -> 0.014815826
A17: 60053-FUNDO DE PROPAGANDA | B17: =IF(B$10=0,0,B7/B$10) -> 0.037132943 | C17: =IF(C$10=0,0,C7/C$10) -> 0.036074601 | D17: =IF(D$10=0,0,D7/D$10) -> 0.037320842 | E17: =IF(E$10=0,0,E7/E$10) -> 0.025363952 | F17: =IF(F$10=0,0,F7/F$10) -> 0.041185542 | G17: =IF(G$10=0,0,G7/G$10) -> 0.035188919
A20: DADOS PARA GRÁFICO (EVOLUÇÃO MENSAL)
A21: Despesa | B21: 46048 | C21: Fev/26 | D21: 46107 | E21: Abr/26 | F21: Mai/26
A22: 60052-ROYALTIES | B22: =B5 -> 2623.02 | C22: =C5 -> 24839.94 | D22: =D5 -> 20571.58 | E22: =E5 -> 26432.78 | F22: =F5 -> 24737.21
A23: 60001-APOSTILA | B23: =B6 -> 0 | C23: =C6 -> 3152.57 | D23: =D6 -> 1993.52 | E23: =E6 -> 15622.75 | F23: =F6 -> 3992.8
A24: 60053-FUNDO DE PROPAGANDA | B24: =B7 -> 11568.26 | C24: =C7 -> 11802.77 | D24: =D7 -> 12392.42 | E24: =E7 -> 9304.76 | F24: =F7 -> 13742.91
A25: % REPRESENTATIVIDADE | B25: =B12 -> 0.045552571 | C25: =C12 -> 0.12163237 | D25: =D12 -> 0.10527759 | E25: =E12 -> 0.1400036 | F25: =F12 -> 0.12728529
A66: 📊 RESUMO ESTATÍSTICO - 2026
A67: Despesa | B67: Total 2026 | C67: Média Mensal | D67: % do Total Franq. | E67: % do Total Geral
A68: 60052-ROYALTIES | B68: =G5 -> 99204.53 | C68: =G5/5 -> 19840.906 | D68: =IF(G8=0,0,G5/G8) -> 0.54276179 | E68: =IF(G10=0,0,G5/G10) -> 0.059357824
A69: 60001-APOSTILA | B69: =G6 -> 24761.64 | C69: =G6/5 -> 4952.328 | D69: =IF(G8=0,0,G6/G8) -> 0.13547438 | E69: =IF(G10=0,0,G6/G10) -> 0.014815826
A70: 60053-FUNDO DE PROPAGANDA | B70: =G7 -> 58811.12 | C70: =G7/5 -> 11762.224 | D70: =IF(G8=0,0,G7/G8) -> 0.32176383 | E70: =IF(G10=0,0,G7/G10) -> 0.035188919
A71: TOTAL FRANQUEADORA | B71: =G8 -> 182777.29 | C71: =G8/5 -> 36555.458 | D71: =IF(G8=0,0,1) -> 1 | E71: =IF(G10=0,0,G8/G10) -> 0.10936257
A73: 🔄 ATUALIZAÇÃO AUTOMÁTICA
A74: Todos os dados desta planilha estão vinculados à BASE e serão atualizados automaticamente.
